Workbook

Sheet Index
B2: UltraTech Cement Ltd
B3: BSE: 532538 | NSE: ULTRACEMCO | ISIN: INE481G01011 | Currency: All Figures in ₹ Crores unless stated
B5: Sheet | C5: Content
B7: Summary | C7: Investment Summary - Output from different valuation methods
B8: Assumptions | C8: Written Assumptions and interpretation behind every forecast driver
B9: Data Sheet | C9: Audited Statement of P/L, B/S, and CFS, FY2022-FY2026
B10: Model | C10: 10-year forecast (FY27E-FY36E): 3-statement model, working capital, historical
C11: & forecast FCFF, DCF valuation, sensitivity analysis, and Comps analysis
B12: Comps Data | C12: All the input of Trading comparables
B13: Ratio Analysis | C13: Profitability ratios, Dupont/earning power, Liquidity, solvency, Activity ratios
B14: Market Return | C14: Daily Nifty 50 index closing prices used to derive the equity market return for CAPM
B15: Beta & WACC | C15: Cost of capital build-up: Regression beta unlevering/relevering, cost of debt, cost of equity (CAPM), WACC
B16: Beta from Regression | C16: Monthly regression of Ultratech Cement stock returns vs Nifty 50 (5-year raw beta)

Sheet Summary
B2: UltraTech Cement Ltd - Investment Summary
B3: BSE: 532538 | NSE: ULTRACEMCO | ISIN: INE481G01011 | Sector: Cement & Building Materials | Industry: Cement & cement products
D5: Equity Value Available
B6: Valuation Method | C6: Enterprise Value | D6: to Equity Shareholders | E6: Value Per Share | F6: Market Price | G6: Discount / Premium | H6: Discount / Premium % | I6: Interpretation
B7: Discounted Cash Flow - Perpetuity Growth | C7: =Model!H235 -> 169660.28 | D7: =Model!H238 -> 146936.26 | E7: =Model!H240 -> 4985.9608 | F7: ='Comps Data'!D3 -> 10675 | G7: =E7-F7 -> -5689.0392 | H7: =G7/F7 -> -0.53293108 | I7: =IF(H7<0,"Overvalued","Undervalued") -> Overvalued
B8: Discounted Cash Flow - Exit Multiple | C8: =Model!I235 -> 266432.03 | D8: =Model!I238 -> 243708.01 | E8: =Model!I240 -> 8269.6982 | F8: =F7 -> 10675 | G8: =E8-F8 -> -2405.3018 | H8: =G8/F8 -> -0.22532101 | I8: =IF(H8<0,"Overvalued","Undervalued") -> Overvalued
B9: Relative Valuation - EV/EBITDA | C9: =Model!D199 -> 246992.02 | D9: =Model!G199 -> 220532.38 | E9: =Model!I199 -> 7483.2841 | F9: =F8 -> 10675 | G9: =E9-F9 -> -3191.7159 | H9: =G9/F9 -> -0.29898978 | I9: =IF(H9<0,"Overvalued","Undervalued") -> Overvalued
B10: Relative Valuation - EV/Sales | C10: =Model!D198 -> 222733.01 | D10: =Model!G198 -> 196273.37 | E10: =Model!I198 -> 6660.1075 | F10: =F9 -> 10675 | G10: =E10-F10 -> -4014.8925 | H10: =G10/F10 -> -0.37610234 | I10: =IF(H10<0,"Overvalued","Undervalued") -> Overvalued
B11: Relative Valuation - Price/Earnings | C11: =Model!D200 -> 244640.68 | D11: =Model!G200 -> 218181.04 | E11: =Model!I200 -> 7403.4964 | F11: =F10 -> 10675 | G11: =E11-F11 -> -3271.5036 | H11: =G11/F11 -> -0.30646404 | I11: =IF(H11<0,"Overvalued","Undervalued") -> Overvalued

Sheet Assumptions
A1: ULTRATECH CEMENT LTD
A3: ASSUMPTIONS
B5: COLOUR CODE
B6: Input / hard-coded figure | C6: Blue
B7: Calculated figure | C7: Black
B10: Ratio Assumption
B11: Scenario switch | C11: Model!D26 selects Base (1), Bull (2) or Bear (3). Only capacity utilisation and realisation growth change by scenario; all other drivers are common. Base case is used for the Summary.
B12: Revenue | C12: Revenue = sales volume x realisation per tonne. Volume = average installed capacity x capacity utilisation (see Operating Data in Model).
B13: Capacity additions (MTPA) | C13: 27.24 MTPA in FY27E, 18.5 in FY28E, 14 in FY29E, tapering to 11 MTPA a year from FY30E, in line with the company's announced expansion pipeline. Capacity grows from 191.4 MTPA (FY26) to 337.1 MTPA (FY36E).
B14: Capacity utilisation | C14: Base 80% in FY27E, 79% in FY28E and 80% in FY29E, rising gradually to 83% by FY36E (FY26 actual 82.3%). Bull is +2 points and Bear is -4 points versus Base. A new plant ramps up slowly, so near-term utilisation is kept slightly below FY26.
B15: Realisation per tonne | C15: Grows 3% a year in Base, in line with long-run inflation. Bull 4%, Bear 1.5%. Realisation was almost flat over FY22-FY26 (Rs 5,596 to Rs 5,738 per tonne), so 3% is not aggressive.
B16: Cost per tonne | C16: COGS (materials, power and fuel) and other expenses per tonne grow 3% a year (inflation). Salaries per tonne grow 5% a year (wage inflation). Costs are driven per tonne, so EBITDA per tonne moves with the realisation-cost gap (Rs 1,103 in FY26 to Rs 1,406 in FY36E).
B17: Depreciation (% of opening PP&E) | C17: FY26 rate of 5.59% held constant. It is applied on opening PP&E so the number does not depend on the current-year capex.
B18: Interest rate on debt | C18: FY26 interest / average debt of 7.82%, held constant. Debt includes lease liabilities.
B19: Other income (% of revenue) | C19: FY26 level of 0.48% held constant. It is small and not a driver of value.
B20: Tax rate | C20: FY26 effective rate of 25.06% in the P&L forecast. The DCF uses 24.6% from the WACC sheet, which is UltraTech's own effective rate.
B21: NCI share of profit | C21: FY26 share of 0.28% held constant. NCI is deducted from profit after tax to get profit attributable to owners.
B22: Dividend payout ratio | C22: FY26 payout of 27.84% of profit attributable to owners, held constant. The ratio is stable at about 15-33% over FY22-FY26, so FY26 is representative.
... B31: Comparable companies / market data | C31: Peer data is taken from Screener for FY26 (sales, EBITDA = operating profit, net profit). Peer EV uses Screener debt and cash and excludes NCI, so peer multiples are on Screener's basis; the median multiple is used to limit the effect of outliers. Ambuja consolidates ACC, so the two overlap. UltraTech CMP is Rs 10,675 and shares are 29.47 crore.
B33: Some important calculation terms
B34: Risk Free Rate | C34: 7.30%, 10-year Government of India bond yield.
B35: Equity Market Return | C35: 11.16%, calculated on the Market Return sheet from Nifty 50 prices.
B36: Equity Risk Premium | C36: 3.86%, calculated as market return minus risk-free rate.

Sheet Data Sheet
B2: UltraTech Cement Ltd
B3: (All figures are in ₹ Crore, Except per share)
A4: # | B4: Income Statement | C4: 2022 | D4: =C4+1 -> 2023 | E4: =D4+1 -> 2024 | F4: =E4+1 -> 2025 | G4: =F4+1 -> 2026
B6: Revenue from Operations | C6: 52598.83 | D6: 63239.98 | E6: 70908.14 | F6: 75955.13 | G6: 88511.53
B7: Other Income | C7: 507.81 | D7: 503.08 | E7: 616.95 | F7: 744.17 | G7: 577.51
B8: TOTAL INCOME (I) | C8: =SUM(C6:C7) -> 53106.64 | D8: =SUM(D6:D7) -> 63743.06 | E8: =SUM(E6:E7) -> 71525.09 | F8: =SUM(F6:F7) -> 76699.3 | G8: =SUM(G6:G7) -> 89089.04
B9: EXPENSES
B10: Cost of Materials Consumed | C10: 7096.49 | D10: 8933.49 | E10: 10252.41 | F10: 11821.72 | G10: 14568.44
B11: Purchases of Stock-in-Trade | C11: 1251.66 | D11: 1299.68 | E11: 1733.86 | F11: 1869.74 | G11: 2516.57
B12: Changes in Inventories of Finished Goods, Stock-in-Trade and Work-in-Progress | C12: -383.16 | D12: -518.21 | E12: -83.35 | F12: 12.27 | G12: 103.35
B13: Employee Benefits Expense | C13: 2534.68 | D13: 2738.97 | E13: 3037.58 | F13: 3604.59 | G13: 4162.44
B14: Finance Costs | C14: 944.71 | D14: 822.72 | E14: 968 | F14: 1650.54 | G14: 1871.71
B15: Depreciation and Amortisation Expense | C15: 2714.75 | D15: 2887.99 | E15: 3145.3 | F15: 4014.95 | G15: 4644.46
B16: Power and Fuel Expense | C16: 12137.26 | D16: 18491.32 | E16: 18283.32 | F16: 18419.15 | G16: 19597.16
B17: Freight and Forwarding Expense | C17: 11712.33 | D17: 14009.16 | E17: 15880.67 | F17: 17459.83 | G17: 19169.13
B18: Other Expenses | C18: 6735.22 | D18: 7665.72 | E18: 8835.09 | F18: 10210.38 | G18: 11374.21
B19: TOTAL EXPENSES (II) | C19: =SUM(C10:C18) -> 44743.94 | D19: =SUM(D10:D18) -> 56330.84 | E19: =SUM(E10:E18) -> 62052.88 | F19: =SUM(F10:F18) -> 69063.17 | G19: =SUM(G10:G18) -> 78007.47
B20: Profit before Exceptional Items, Share in Profit / (Loss) of Associates and Joint Venture and Tax expense | C20: =C8-C19 -> 8362.7 | D20: =D8-D19 -> 7412.22 | E20: =E8-E19 -> 9472.21 | F20: =F8-F19 -> 7636.13 | G20: =G8-G19 -> 11081.57
B22: Exceptional Items :
B23: Provision for Impairment in value of Investment | F23: 9.35 | G23: 50.07
B24: Statutory Impact of New Labour Codes | G24: 88.48
B25: Stamp duty on Business Combination | E25: 72 | F25: 88.08
B26: Profit before Share in Profit / (Loss) of Associates and Joint Venture and Tax Expense | C26: =C20-SUM(C23:C25) -> 8362.7 | D26: =D20-SUM(D23:D25) -> 7412.22 | E26: =E20-SUM(E23:E25) -> 9400.21 | F26: =F20-SUM(F23:F25) -> 7538.7 | G26: =G20-SUM(G23:G25) -> 10943.02
B27: Share in Profit / (Loss) of Associate and Joint Venture (net of Tax expense) | C27: 1.7 | D27: 4.03 | E27: 22.01 | F27: -10.57 | G27: -15.83
B28: Profit before Tax Expense | C28: =SUM(C26:C27) -> 8364.4 | D28: =SUM(D26:D27) -> 7416.25 | E28: =SUM(E26:E27) -> 9422.22 | F28: =F26+F27 -> 7528.13 | G28: =G26+G27 -> 10927.19
B29: Tax Expense:
B30: Current Tax Charge | C30: 1211.22 | D30: 2070.77 | E30: 2218.48 | F30: 828.29 | G30: 2313.62
B31: Deferred Tax Charge | C31: -21.16 | D31: 272.08 | E31: 199.78 | F31: 660.2 | G31: 425.22
B32: Total Tax Expense | C32: =SUM(C30:C31) -> 1190.06 | D32: =SUM(D30:D31) -> 2342.85 | E32: =SUM(E30:E31) -> 2418.26 | F32: =SUM(F30:F31) -> 1488.49 | G32: =SUM(G30:G31) -> 2738.84
B33: Profit for the period (III) | C33: =C28-C32 -> 7174.34 | D33: =D28-D32 -> 5073.4 | E33: =E28-E32 -> 7003.96 | F33: =F28-F32 -> 6039.64 | G33: =G28-G32 -> 8188.35
B34: Profit / (Loss) attributable to Non-Controlling Interest | C34: -10.05 | D34: 9.44 | E34: -1.04 | F34: 0.53 | G34: 22.71
B36: Basic EPS | C36: 254.64 | D36: 175.63 | E36: 243.05 | F36: 205.3 | G36: 277.62
B37: Diluted EPS | C37: 254.53 | D37: 175.54 | E37: 242.87 | F37: 205.13 | G37: 277.45
A39: # | B39: Balance Sheet | C39: 2022 | D39: =C39+1 -> 2023 | E39: =D39+1 -> 2024 | F39: =E39+1 -> 2025 | G39: =F39+1 -> 2026
B41: ASSETS
B42: Non-Current Assets
B43: Property, Plant and Equipment | C43: 42592.19 | D43: 46480.28 | E43: 50126.09 | F43: 76015.19 | G43: 80283.38
B44: Capital Work-in-Progress | C44: 4777.25 | D44: 4034.91 | E44: 6782.77 | F44: 6188.27 | G44: 8275.87
B45: Right of Use Assets | C45: 1178.6 | D45: 1190.36 | E45: 916.27 | F45: 835.73 | G45: 714.34
B46: Goodwill | C46: 6250.21 | D46: 6329.26 | E46: 6345.49 | F46: 7681.78 | G46: 7909.05
B47: Other Intangible Assets | C47: 5466.57 | D47: 5579.1 | E47: 5489.76 | F47: 10031.52 | G47: 9886.78
B48: Intangible Assets under development | C48: 7.42 | D48: 5.48 | E48: 28.41 | F48: 45.92 | G48: 466.4
B50: Investments Accounted using Equity Method | C50: 30.17 | D50: 876.01 | E50: 968.94 | F50: 300.12 | G50: 319.41
B51: Financial Assets:
B52: Investments | C52: 1342.26 | D52: 584.34 | E52: 1795.21 | F52: 1997.28 | G52: 2684.48
B53: Loans | C53: 9.59 | D53: 9.22 | E53: 8.31 | F53: 16.21 | G53: 17.21
B54: Other Financial Assets | C54: 1109.98 | D54: 1881.11 | E54: 1457.23 | F54: 2933.16 | G54: 3063.39
B56: Income Tax Assets (Net) | C56: 479.46 | D56: 401.94 | E56: 4.9 | F56: 857.91 | G56: 266.26
B57: Deferred Tax Assets (Net) | C57: 16.35 | D57: 6.56 | E57: 456.03 | F57: 65.09 | G57: 60.95
B58: Other Non-Current Assets | C58: 3078.27 | D58: 3265.49 | E58: 3264.23 | F58: 2991.77 | G58: 2181.09
B59: Total Non-Current Assets | C59: =SUM(C43:C58) -> 66338.32 | D59: =SUM(D43:D58) -> 70644.06 | E59: =SUM(E43:E58) -> 77643.64 | F59: =SUM(F43:F58) -> 109959.95 | G59: =SUM(G43:G58) -> 116128.61
B60: Current Assets
B61: Inventories | C61: 5595.58 | D61: 6611.83 | E61: 8329.74 | F61: 9562.98 | G61: 9694.28
B62: Financial Assets
B63: Investments | C63: 4963.34 | D63: 5836.6 | E63: 5484.8 | F63: 2859.07 | G63: 3735.62
B64: Trade Receivables | C64: 3071.61 | D64: 3867.02 | E64: 4278.16 | F64: 5890.25 | G64: 6028.75
B65: Cash and Cash Equivalents | C65: 120.54 | D65: 370.37 | E65: 553.58 | F65: 467.21 | G65: 354.48
B66: Bank Balances other than Cash and Cash Equivalents | C66: 238.64 | D66: 779.22 | E66: 229.63 | F66: 1206.11 | G66: 1029.87
B67: Loans | C67: 6.86 | D67: 7.67 | E67: 8.91 | F67: 10 | G67: 13.37
B68: Other Financial Assets | C68: 1871.95 | D68: 1433.82 | E68: 2310.35 | F68: 1298.68 | G68: 1535.87
B70: Income Tax Assets (Net) | C70: 0.09 | D70: 0.07 | E70: 0.07 | F70: 58 | G70: 64.45
B71: Other Current Assets | C71: 1611.33 | D71: 1818.28 | E71: 1948.23 | F71: 2247.21 | G71: 2645.06
B72: Total Current Assets | C72: =SUM(C61:C71) -> 17479.94 | D72: =SUM(D61:D71) -> 20724.88 | E72: =SUM(E61:E71) -> 23143.47 | F72: =SUM(F61:F71) -> 23599.51 | G72: =SUM(G61:G71) -> 25101.75
B73: Asset Held for Sale | C73: 9.53 | D73: 18.02 | E73: 14.9 | F73: 137.69 | G73: 145.69
B74: TOTAL ASSETS | C74: =SUM(C59,C72:C73) -> 83827.79 | D74: =SUM(D59,D72:D73) -> 91386.96 | E74: =SUM(E59,E72:E73) -> 100802.01 | F74: =SUM(F59,F72:F73) -> 133697.15 | G74: =SUM(G59,G72:G73) -> 141376.05
B75: EQUITY AND LIABILITIES
B76: EQUITY
B77: Equity Share Capital | C77: 288.67 | D77: 288.69 | E77: 288.69 | F77: 294.68 | G77: 294.68
B78: Other Equity | C78: 50146.6 | D78: 54035.85 | E78: 59938.78 | F78: 70411.53 | G78: 76328.86
B79: Non-Controlling Interest | C79: -3.06 | D79: 55.63 | E79: 55.94 | F79: 3186.59 | G79: 4088.9
B80: Total Equity | C80: =SUM(C77:C79) -> 50432.21 | D80: =SUM(D77:D79) -> 54380.17 | E80: =SUM(E77:E79) -> 60283.41 | F80: =SUM(F77:F79) -> 73892.8 | G80: =SUM(G77:G79) -> 80712.44
B81: Share Application Money Pending Allotment | E81: 0.01 | F81: 0.56
B82: LIABILITIES
B83: Non-Current Liabilities
B84: Financial Liabilities
B85: Borrowings | C85: 5303 | D85: 5356.41 | E85: 5307.78 | F85: 15780.77 | G85: 15018.82
B86: Lease Liabilities | C86: 978.2 | D86: 1010.65 | E86: 942.11 | F86: 868.21 | G86: 751.72
B87: Other Financial Liabilities | C87: 303.48 | D87: 319.84 | E87: 240.86 | F87: 287.82 | G87: 236.35
B89: Provisions | C89: 617.84 | D89: 624.21 | E89: 670.57 | F89: 892.09 | G89: 934.96
B90: Deferred Tax Liabilities (Net) | C90: 6033.24 | D90: 6260.11 | E90: 6447.78 | F90: 9579.44 | G90: 9890.06
B91: Other Non-Current Liabilities | C91: 4.63 | D91: 3.78 | E91: 3.53 | F91: 30.49
B92: Total Non-Current Liabilities | C92: =SUM(C85:C91) -> 13240.39 | D92: =SUM(D85:D91) -> 13575 | E92: =SUM(E85:E91) -> 13612.63 | F92: =SUM(F85:F91) -> 27438.82 | G92: =SUM(G85:G91) -> 26831.91
B93: Current Liabilities
B94: Financial Liabilities
B95: Borrowings | C95: 4899.84 | D95: 4544.37 | E95: 4990.61 | F95: 7250.22 | G95: 7761.84
B96: Lease Liabilities | C96: 117.76 | D96: 146.31 | E96: 162.45 | F96: 202.98 | G96: 222.71
B97: Trade Payables
B98: Total outstanding dues of Micro and Small Enterprises | C98: 124.47 | D98: 183.4 | E98: 254.19 | F98: 272.52 | G98: 518.62
B99: Total outstanding dues of creditors other than Micro and Small Enterprises | C99: 5738.36 | D99: 7025.9 | E99: 8224.14 | F99: 9054.96 | G99: 9718.09
B101: Other Financial Liabilities | C101: 3608.55 | D101: 4783.56 | E101: 5326.92 | F101: 6552.32 | G101: 6510.58
B103: Other Current Liabilities | C103: 4890.94 | D103: 5177.4 | E103: 5706.68 | F103: 6692.18 | G103: 6311.87
B104: Provisions | C104: 247.98 | D104: 204.43 | E104: 257.5 | F104: 350.21 | G104: 354.84
B105: Current Tax Liabilities (Net) | C105: 527.29 | D105: 1366.42 | E105: 1983.47 | F105: 1989.58 | G105: 2433.15
B106: Total Current Liabilities | C106: =SUM(C95:C105) -> 20155.19 | D106: =SUM(D95:D105) -> 23431.79 | E106: =SUM(E95:E105) -> 26905.96 | F106: =SUM(F95:F105) -> 32364.97 | G106: =SUM(G95:G105) -> 33831.7
B107: TOTAL EQUITY AND LIABILITIES | C107: =SUM(C80,C81,C92,C106) -> 83827.79 | D107: =SUM(D80,D81,D92,D106) -> 91386.96 | E107: =SUM(E80,E81,E92,E106) -> 100802.01 | F107: =SUM(F80,F81,F92,F106) -> 133697.15 | G107: =SUM(G80,G81,G92,G106) -> 141376.05
A109: # | B109: Cash Flow Statement | C109: 2022 | D109: =C109+1 -> 2023 | E109: =D109+1 -> 2024 | F109: =E109+1 -> 2025 | G109: =F109+1 -> 2026
B111: (A) Cash Flows from Operating Activities:
B112: Profit Before tax | C112: 8364.4 | D112: 7416.25 | E112: 9422.22 | F112: 7528.13 | G112: 10927.19
B113: Adjustments for:
B114: Depreciation and Amortisation Expense (Refer Note 32) | C114: 2714.75 | D114: 2887.99 | E114: 3145.3 | F114: 4014.95 | G114: 4644.46
...

Sheet Model
B2: ='Data Sheet'!B2 -> UltraTech Cement Ltd
B3: Financial Statement & DCF Analysis | C3: 2022 | D3: =C3+1 -> 2023 | E3: =D3+1 -> 2024 | F3: =E3+1 -> 2025 | G3: =F3+1 -> 2026 | H3: =G3+1 -> 2027 | I3: =H3+1 -> 2028 | J3: =I3+1 -> 2029 | K3: =J3+1 -> 2030 | ... Q3: =P3+1 -> 2036
B4: (All figures are in ₹ Crore, Except per share)
A5: # | B5: Income Statement
B7: Revenue | C7: ='Data Sheet'!C6 -> 52598.83 | D7: ='Data Sheet'!D6 -> 63239.98 | E7: ='Data Sheet'!E6 -> 70908.14 | F7: ='Data Sheet'!F6 -> 75955.13 | G7: ='Data Sheet'!G6 -> 88511.53 | H7: =H150*H152/10 -> 96919.993 | I7: =I150*I152/10 -> 109578.47 | J7: =J150*J152/10 -> 122445.86 | K7: =K150*K152/10 -> 135019.53 | L7: =L150*L152/10 -> 148150.94 | M7: =M150*M152/10 -> 161849.37 | N7: =N150*N152/10 -> 174026.74 | O7: =O150*O152/10 -> 186487.43 | ... Q7: =Q150*Q152/10 -> 212246.01
B8: COGS | C8: =-SUM('Data Sheet'!C10:C12,'Data Sheet'!C16) -> -20102.25 | D8: =-SUM('Data Sheet'!D10:D12,'Data Sheet'!D16) -> -28206.28 | E8: =-SUM('Data Sheet'!E10:E12,'Data Sheet'!E16) -> -30186.24 | F8: =-SUM('Data Sheet'!F10:F12,'Data Sheet'!F16) -> -32122.88 | G8: =-SUM('Data Sheet'!G10:G12,'Data Sheet'!G16) -> -36785.52 | H8: =-H150*H156/10 -> -40280.09 | I8: =-I150*I156/10 -> -45540.973 | J8: =-J150*J156/10 -> -50888.678 | K8: =-K150*K156/10 -> -56114.313 | L8: =-L150*L156/10 -> -61571.746 | M8: =-M150*M156/10 -> -67264.832 | N8: =-N150*N156/10 -> -72325.766 | O8: =-O150*O156/10 -> -77504.447 | ... Q8: =-Q150*Q156/10 -> -88209.749
B9: Gross Profit | C9: =SUM(C7:C8) -> 32496.58 | D9: =SUM(D7:D8) -> 35033.7 | E9: =SUM(E7:E8) -> 40721.9 | F9: =SUM(F7:F8) -> 43832.25 | G9: =SUM(G7:G8) -> 51726.01 | H9: =SUM(H7:H8) -> 56639.904 | I9: =SUM(I7:I8) -> 64037.502 | J9: =SUM(J7:J8) -> 71557.185 | ... Q9: =SUM(Q7:Q8) -> 124036.26
B10: Salaries & Benefits | C10: =-'Data Sheet'!C13 -> -2534.68 | D10: =-'Data Sheet'!D13 -> -2738.97 | E10: =-'Data Sheet'!E13 -> -3037.58 | F10: =-'Data Sheet'!F13 -> -3604.59 | G10: =-'Data Sheet'!G13 -> -4162.44 | H10: =-H158*H150/10 -> -4646.3678 | I10: =-I158*I150/10 -> -5355.2227 | J10: =-J158*J150/10 -> -6100.2619 | K10: =-K158*K150/10 -> -6857.2982 | L10: =-L158*L150/10 -> -7670.3102 | M10: =-M158*M150/10 -> -8542.2366 | N10: =-N158*N150/10 -> -9363.2938 | O10: =-O158*O150/10 -> -10228.555 | ... Q10: =-Q158*Q150/10 -> -12097.856
B11: Other SG&A Expenses | C11: =-SUM('Data Sheet'!C17:C18) -> -18447.55 | D11: =-SUM('Data Sheet'!D17:D18) -> -21674.88 | E11: =-SUM('Data Sheet'!E17:E18) -> -24715.76 | F11: =-SUM('Data Sheet'!F17:F18) -> -27670.21 | G11: =-SUM('Data Sheet'!G17:G18) -> -30543.34 | H11: =-H150*H160/10 -> -33444.912 | I11: =-I150*I160/10 -> -37813.069 | J11: =-J150*J160/10 -> -42253.316 | K11: =-K150*K160/10 -> -46592.206 | L11: =-L150*L160/10 -> -51123.561 | M11: =-M150*M160/10 -> -55850.58 | N11: =-N150*N160/10 -> -60052.718 | O11: =-O150*O160/10 -> -64352.622 | ... Q11: =-Q150*Q160/10 -> -73241.329
B12: EBITDA | C12: =SUM(C9:C11) -> 11514.35 | D12: =SUM(D9:D11) -> 10619.85 | E12: =SUM(E9:E11) -> 12968.56 | F12: =SUM(F9:F11) -> 12557.45 | G12: =SUM(G9:G11) -> 17020.23 | H12: =SUM(H9:H11) -> 18548.624 | I12: =SUM(I9:I11) -> 20869.21 | J12: =SUM(J9:J11) -> 23203.607 | ... Q12: =SUM(Q9:Q11) -> 38697.076
B13: Depreciation & Amortization | C13: =-'Data Sheet'!C15 -> -2714.75 | D13: =-'Data Sheet'!D15 -> -2887.99 | E13: =-'Data Sheet'!E15 -> -3145.3 | F13: =-'Data Sheet'!F15 -> -4014.95 | G13: =-'Data Sheet'!G15 -> -4644.46 | H13: =H120 -> -4993.1559 | I13: =I120 -> -5269.748 | J13: =J120 -> -5558.4535 | K13: =K120 -> -5743.7645 | L13: =L120 -> -5943.5528 | M13: =M120 -> -6130.7342 | N13: =N120 -> -6333.3861 | O13: =O120 -> -6520.3807 | ... Q13: =Q120 -> -6905.2107
B14: EBIT | C14: =SUM(C12:C13) -> 8799.6 | D14: =SUM(D12:D13) -> 7731.86 | E14: =SUM(E12:E13) -> 9823.26 | F14: =SUM(F12:F13) -> 8542.5 | G14: =SUM(G12:G13) -> 12375.77 | H14: =SUM(H12:H13) -> 13555.468 | I14: =SUM(I12:I13) -> 15599.462 | J14: =SUM(J12:J13) -> 17645.154 | ... Q14: =SUM(Q12:Q13) -> 31791.866
B15: Interest Expense | C15: =-'Data Sheet'!C14 -> -944.71 | D15: =-'Data Sheet'!D14 -> -822.72 | E15: =-'Data Sheet'!E14 -> -968 | F15: =-'Data Sheet'!F14 -> -1650.54 | G15: =-'Data Sheet'!G14 -> -1871.71 | H15: =H127 -> -1858.1352 | I15: =I127 -> -1858.1352 | J15: =J127 -> -1779.9147 | K15: =K127 -> -1584.3634 | L15: =L127 -> -1388.8122 | M15: =M127 -> -1193.2609 | N15: =N127 -> -997.70963 | O15: =O127 -> -841.26861 | ... Q15: =Q127 -> -567.49683
B16: Other Income | C16: ='Data Sheet'!C7+'Data Sheet'!C27-SUM('Data Sheet'!C23:C25) -> 509.51 | D16: ='Data Sheet'!D7+'Data Sheet'!D27-SUM('Data Sheet'!D23:D25) -> 507.11 | E16: ='Data Sheet'!E7+'Data Sheet'!E27-SUM('Data Sheet'!E23:E25) -> 566.96 | F16: ='Data Sheet'!F7+'Data Sheet'!F27-SUM('Data Sheet'!F23:F25) -> 636.17 | G16: ='Data Sheet'!G7+'Data Sheet'!G27-SUM('Data Sheet'!G23:G25) -> 423.13 | H16: =H7*H33 -> 463.32672 | I16: =I7*I33 -> 523.84068 | J16: =J7*J33 -> 585.35332 | K16: =K7*K33 -> 645.46183 | L16: =L7*L33 -> 708.23663 | M16: =M7*M33 -> 773.72206 | N16: =N7*N33 -> 831.93609 | O16: =O7*O33 -> 891.5045 | ... Q16: =Q7*Q33 -> 1014.6436
B17: EBT | C17: =SUM(C14:C16) -> 8364.4 | D17: =SUM(D14:D16) -> 7416.25 | E17: =SUM(E14:E16) -> 9422.22 | F17: =SUM(F14:F16) -> 7528.13 | G17: =SUM(G14:G16) -> 10927.19 | H17: =SUM(H14:H16) -> 12160.66 | I17: =SUM(I14:I16) -> 14265.167 | J17: =SUM(J14:J16) -> 16450.592 | ... Q17: =SUM(Q14:Q16) -> 32239.012
B18: Tax | C18: =-'Data Sheet'!C32 -> -1190.06 | D18: =-'Data Sheet'!D32 -> -2342.85 | E18: =-'Data Sheet'!E32 -> -2418.26 | F18: =-'Data Sheet'!F32 -> -1488.49 | G18: =-'Data Sheet'!G32 -> -2738.84 | H18: =-H17*H34 -> -3048.0024 | I18: =-I17*I34 -> -3575.4857 | J18: =-J17*J34 -> -4123.2504 | K18: =-K17*K34 -> -4705.3612 | L18: =-L17*L34 -> -5303.9374 | M18: =-M17*M34 -> -5925.5986 | N18: =-N17*N34 -> -6463.07 | O18: =-O17*O34 -> -7000.9175 | ... Q18: =-Q17*Q34 -> -8080.5309
B19: Net Profit | C19: =SUM(C17:C18) -> 7174.34 | D19: =SUM(D17:D18) -> 5073.4 | E19: =SUM(E17:E18) -> 7003.96 | F19: =SUM(F17:F18) -> 6039.64 | G19: =SUM(G17:G18) -> 8188.35 | H19: =SUM(H17:H18) -> 9112.6574 | I19: =SUM(I17:I18) -> 10689.682 | J19: =SUM(J17:J18) -> 12327.342 | ... Q19: =SUM(Q17:Q18) -> 24158.482
B21: Less : Profit attributable to NCI | C21: =-'Data Sheet'!C34 -> 10.05 | D21: =-'Data Sheet'!D34 -> -9.44 | E21: =-'Data Sheet'!E34 -> 1.04 | F21: =-'Data Sheet'!F34 -> -0.53 | G21: =-'Data Sheet'!G34 -> -22.71 | H21: =-H19*H40 -> -25.273523 | I21: =-I19*I40 -> -29.647325 | J21: =-J19*J40 -> -34.189298 | K21: =-K19*K40 -> -39.016063 | L21: =-L19*L40 -> -43.979356 | M21: =-M19*M40 -> -49.134065 | N21: =-N19*N40 -> -53.590688 | O21: =-O19*O40 -> -58.050429 | ... Q21: =-Q19*Q40 -> -67.002402
B22: Net profit attributable to owners | C22: =C19+C21 -> 7184.39 | D22: =D19+D21 -> 5063.96 | E22: =E19+E21 -> 7005 | F22: =F19+F21 -> 6039.11 | G22: =G19+G21 -> 8165.64 | H22: =H19+H21 -> 9087.3839 | I22: =I19+I21 -> 10660.034 | J22: =J19+J21 -> 12293.153 | ... Q22: =Q19+Q21 -> 24091.479
A24: # | B24: Ratios & Assumptions
B26: Scenario | D26: 1
B27: Revenue Growth | C27: NA | D27: =D7/C7-1 -> 0.20230773 | E27: =E7/D7-1 -> 0.12125494 | F27: =F7/E7-1 -> 0.071176454 | G27: =G7/F7-1 -> 0.16531339 | H27: =H7/G7-1 -> 0.094998509 | I27: =I7/H7-1 -> 0.13060753 | J27: =J7/I7-1 -> 0.11742624 | K27: =K7/J7-1 -> 0.10268758 | ... Q27: =Q7/P7-1 -> 0.065339988
B28: COGS as % of Sales | C28: =-C8/C7 -> 0.38218055 | D28: =-D8/D7 -> 0.44601975 | E28: =-E8/E7 -> 0.42570909 | F28: =-F8/F7 -> 0.42291916 | G28: =-G8/G7 -> 0.41560145 | H28: =-H8/H7 -> 0.41560145 | I28: =-I8/I7 -> 0.41560145 | J28: =-J8/J7 -> 0.41560145 | ... Q28: =-Q8/Q7 -> 0.41560145
B29: Salaries & benefits as % of Revenue | C29: =-C10/C7 -> 0.048188905 | D29: =-D10/D7 -> 0.043310735 | E29: =-E10/E7 -> 0.042838241 | F29: =-F10/F7 -> 0.047456834 | G29: =-G10/G7 -> 0.047027094 | H29: =-H10/H7 -> 0.047940241 | I29: =-I10/I7 -> 0.048871119 | J29: =-J10/J7 -> 0.049820073 | ... Q29: =-Q10/Q7 -> 0.056999216
B30: Other SG&A Expenses as % of Revenue | C30: =-C11/C7 -> 0.35072168 | D30: =-D11/D7 -> 0.34274015 | E30: =-E11/E7 -> 0.34856026 | F30: =-F11/F7 -> 0.36429679 | G30: =-G11/G7 -> 0.34507753 | H30: =-H11/H7 -> 0.34507753 | I30: =-I11/I7 -> 0.34507753 | J30: =-J11/J7 -> 0.34507753 | ... Q30: =-Q11/Q7 -> 0.34507753
B31: D&A as % of opening PP&E | C31: NA | D31: =-D120/D117 -> 0.059487263 | E31: =-E120/E117 -> 0.060830994 | F31: =-F120/F117 -> 0.069432615 | G31: =-G120/G117 -> 0.055930941 | H31: =G31 -> 0.055930941 | I31: =H31 -> 0.055930941 | J31: =I31 -> 0.055930941 | K31: =J31 -> 0.055930941 | L31: =K31 -> 0.055930941 | M31: =L31 -> 0.055930941 | N31: =M31 -> 0.055930941 | O31: =N31 -> 0.055930941 | ... Q31: =P31 -> 0.055930941
B32: Interest as % of average debt | C32: NA | D32: =-D127/AVERAGE(D124,D126) -> 0.07359994 | E32: =-E127/AVERAGE(E124,E126) -> 0.086195037 | F32: =-F127/AVERAGE(F124,F126) -> 0.092974734 | G32: =-G127/AVERAGE(G124,G126) -> 0.078220509 | H32: =G32 -> 0.078220509 | I32: =H32 -> 0.078220509 | J32: =I32 -> 0.078220509 | K32: =J32 -> 0.078220509 | L32: =K32 -> 0.078220509 | M32: =L32 -> 0.078220509 | N32: =M32 -> 0.078220509 | O32: =N32 -> 0.078220509 | ... Q32: =P32 -> 0.078220509
B33: Other Income (Expense) as % of Revenue | C33: =C16/C7 -> 0.0096867174 | D33: =D16/D7 -> 0.0080188197 | E33: =E16/E7 -> 0.007995697 | F33: =F16/F7 -> 0.0083756028 | G33: =G16/G7 -> 0.0047805071 | H33: =G33 -> 0.0047805071 | I33: =H33 -> 0.0047805071 | J33: =I33 -> 0.0047805071 | K33: =J33 -> 0.0047805071 | L33: =K33 -> 0.0047805071 | M33: =L33 -> 0.0047805071 | N33: =M33 -> 0.0047805071 | O33: =N33 -> 0.0047805071 | ... Q33: =P33 -> 0.0047805071
B34: Taxes Rate | C34: =-C18/C17 -> 0.14227679 | D34: =-D18/D17 -> 0.31590764 | E34: =-E18/E17 -> 0.25665501 | F34: =-F18/F17 -> 0.19772374 | G34: =-G18/G17 -> 0.25064449 | H34: =G34 -> 0.25064449 | I34: =H34 -> 0.25064449 | J34: =I34 -> 0.25064449 | K34: =J34 -> 0.25064449 | L34: =K34 -> 0.25064449 | M34: =L34 -> 0.25064449 | N34: =M34 -> 0.25064449 | O34: =N34 -> 0.25064449 | ... Q34: =P34 -> 0.25064449
B35: Dividend payout ratio | C35: =-C99/C22 -> 0.14823806 | D35: =-D99/D22 -> 0.21549736 | E35: =-E99/E22 -> 0.15623555 | F35: =-F99/F22 -> 0.33310372 | G35: =-G99/G22 -> 0.27840561 | H35: =G35 -> 0.27840561 | I35: =H35 -> 0.27840561 | J35: =I35 -> 0.27840561 | K35: =J35 -> 0.27840561 | L35: =K35 -> 0.27840561 | M35: =L35 -> 0.27840561 | N35: =M35 -> 0.27840561 | O35: =N35 -> 0.27840561 | ... Q35: =P35 -> 0.27840561
B36: DSO | C36: NA | D36: =(AVERAGE(C47:D47)/D7)*365 -> 20.023725 | E36: =(AVERAGE(D47:E47)/E7)*365 -> 20.963677 | F36: =(AVERAGE(E47:F47)/F7)*365 -> 24.431988 | G36: =(AVERAGE(F47:G47)/G7)*365 -> 24.575527 | H36: =AVERAGE(F36:G36) -> 24.503758 | I36: =AVERAGE(G36:H36) -> 24.539642 | J36: =AVERAGE(H36:I36) -> 24.5217 | K36: =AVERAGE(I36:J36) -> 24.530671 | L36: =AVERAGE(J36:K36) -> 24.526186 | M36: =AVERAGE(K36:L36) -> 24.528428 | N36: =AVERAGE(L36:M36) -> 24.527307 | O36: =AVERAGE(M36:N36) -> 24.527868 | ... Q36: =AVERAGE(O36:P36) -> 24.527727
B37: DIO | C37: NA | D37: =-(AVERAGE(C48:D48)/D8)*365 -> 78.984266 | E37: =-(AVERAGE(D48:E48)/E8)*365 -> 90.333759 | F37: =-(AVERAGE(E48:F48)/F8)*365 -> 101.65407 | G37: =-(AVERAGE(F48:G48)/G8)*365 -> 95.53895 | H37: =AVERAGE(F37:G37) -> 98.596508 | I37: =AVERAGE(G37:H37) -> 97.067729 | J37: =AVERAGE(H37:I37) -> 97.832119 | K37: =AVERAGE(I37:J37) -> 97.449924 | L37: =AVERAGE(J37:K37) -> 97.641021 | M37: =AVERAGE(K37:L37) -> 97.545473 | N37: =AVERAGE(L37:M37) -> 97.593247 | O37: =AVERAGE(M37:N37) -> 97.56936 | ... Q37: =AVERAGE(O37:P37) -> 97.575332
B38: DPO | C38: NA | D38: =-AVERAGE(C60:D60)/D8*365 -> 84.579169 | E38: =-AVERAGE(D60:E60)/E8*365 -> 94.844289 | F38: =-AVERAGE(E60:F60)/F8*365 -> 101.1603 | G38: =-AVERAGE(F60:G60)/G8*365 -> 97.061688 | H38: =AVERAGE(F38:G38) -> 99.110996 | I38: =AVERAGE(G38:H38) -> 98.086342 | J38: =AVERAGE(H38:I38) -> 98.598669 | K38: =AVERAGE(I38:J38) -> 98.342506 | L38: =AVERAGE(J38:K38) -> 98.470588 | M38: =AVERAGE(K38:L38) -> 98.406547 | N38: =AVERAGE(L38:M38) -> 98.438567 | O38: =AVERAGE(M38:N38) -> 98.422557 | ... Q38: =AVERAGE(O38:P38) -> 98.42656
B39: Capital Asset Turnover Ratio | C39: NA | D39: =D7/AVERAGE(C52:D52) -> 1.2616003 | E39: =E7/AVERAGE(D52:E52) -> 1.2947631 | F39: =F7/AVERAGE(E52:F52) -> 1.0784155 | G39: =G7/AVERAGE(F52:G52) -> 1.0273356 | H39: =H7/AVERAGE(G52:H52) -> 1.0563923 | I39: =I7/AVERAGE(H52:I52) -> 1.132012 | J39: =J7/AVERAGE(I52:J52) -> 1.2118882 | K39: =K7/AVERAGE(J52:K52) -> 1.2923016 | ... Q39: =Q7/AVERAGE(P52:Q52) -> 1.6948132
B40: NCI Share of net profit | C40: =-C21/C19 -> -0.0014008257 | D40: =-D21/D19 -> 0.0018606851 | E40: =-E21/E19 -> -0.00014848743 | F40: =-F21/F19 -> 8.7753575e-05 | G40: =-G21/G19 -> 0.0027734525 | H40: =G40 -> 0.0027734525 | I40: =H40 -> 0.0027734525 | J40: =I40 -> 0.0027734525 | K40: =J40 -> 0.0027734525 | L40: =K40 -> 0.0027734525 | M40: =L40 -> 0.0027734525 | N40: =M40 -> 0.0027734525 | O40: =N40 -> 0.0027734525 | ... Q40: =P40 -> 0.0027734525
A42: # | B42: Balance Sheet
B44: Current Assets
B45: Cash | C45: ='Data Sheet'!C65 -> 120.54 | D45: ='Data Sheet'!D65 -> 370.37 | E45: ='Data Sheet'!E65 -> 553.58 | F45: ='Data Sheet'!F65 -> 467.21 | G45: ='Data Sheet'!G65 -> 354.48 | H45: =H105 -> 1028.4254 | I45: =I105 -> 1798.2051 | J45: =J105 -> 4010.5561 | K45: =K105 -> 7282.8262 | L45: =L105 -> 12012.938 | M45: =M105 -> 17784.306 | N45: =N105 -> 25590.11 | O45: =O105 -> 34294.408 | ... Q45: =Q105 -> 56490.125
B46: Bank Deposits | C46: ='Data Sheet'!C66 -> 238.64 | D46: ='Data Sheet'!D66 -> 779.22 | E46: ='Data Sheet'!E66 -> 229.63 | F46: ='Data Sheet'!F66 -> 1206.11 | G46: ='Data Sheet'!G66 -> 1029.87 | H46: =G46 -> 1029.87 | I46: =H46 -> 1029.87 | J46: =I46 -> 1029.87 | K46: =J46 -> 1029.87 | L46: =K46 -> 1029.87 | M46: =L46 -> 1029.87 | N46: =M46 -> 1029.87 | O46: =N46 -> 1029.87 | ... Q46: =P46 -> 1029.87
B47: Account Receivable | C47: ='Data Sheet'!C64 -> 3071.61 | D47: ='Data Sheet'!D64 -> 3867.02 | E47: ='Data Sheet'!E64 -> 4278.16 | F47: ='Data Sheet'!F64 -> 5890.25 | G47: ='Data Sheet'!G64 -> 6028.75 | H47: =H7*H36/365 -> 6506.5863 | I47: =I7*I36/365 -> 7367.1687 | J47: =J7*J36/365 -> 8226.2485 | K47: =K7*K36/365 -> 9074.3006 | L47: =L7*L36/365 -> 9955.0068 | M47: =M7*M36/365 -> 10876.468 | N47: =N7*N36/365 -> 11694.267 | O47: =O7*O36/365 -> 12531.888 | ... Q47: =Q7*Q36/365 -> 14262.773
B48: Inventory | C48: ='Data Sheet'!C61 -> 5595.58 | D48: ='Data Sheet'!D61 -> 6611.83 | E48: ='Data Sheet'!E61 -> 8329.74 | F48: ='Data Sheet'!F61 -> 9562.98 | G48: ='Data Sheet'!G61 -> 9694.28 | H48: =-H8*H37/365 -> 10880.757 | I48: =-I8*I37/365 -> 12111.12 | J48: =-J8*J37/365 -> 13639.855 | K48: =-K8*K37/365 -> 14981.741 | L48: =-L8*L37/365 -> 16471.036 | M48: =-M8*M37/365 -> 17976.383 | N48: =-N8*N37/365 -> 19338.374 | O48: =-O8*O37/365 -> 20717.971 | ... Q48: =-Q8*Q37/365 -> 23581.084
B49: Other current assets | C49: ='Data Sheet'!C71 -> 1611.33 | D49: ='Data Sheet'!D71 -> 1818.28 | E49: ='Data Sheet'!E71 -> 1948.23 | F49: ='Data Sheet'!F71 -> 2247.21 | G49: ='Data Sheet'!G71 -> 2645.06 | H49: =G49 -> 2645.06 | I49: =H49 -> 2645.06 | J49: =I49 -> 2645.06 | K49: =J49 -> 2645.06 | L49: =K49 -> 2645.06 | M49: =L49 -> 2645.06 | N49: =M49 -> 2645.06 | O49: =N49 -> 2645.06 | ... Q49: =P49 -> 2645.06
B51: Non Current Assets
B52: Property, Plant & Equipment | C52: =SUM('Data Sheet'!C43:C45) -> 48548.04 | D52: =SUM('Data Sheet'!D43:D45) -> 51705.55 | E52: =SUM('Data Sheet'!E43:E45) -> 57825.13 | F52: =SUM('Data Sheet'!F43:F45) -> 83039.19 | G52: =SUM('Data Sheet'!G43:G45) -> 89273.59 | H52: =H121 -> 94218.834 | I52: =I121 -> 99380.655 | J52: =J121 -> 102693.87 | K52: =K121 -> 106265.92 | L52: =L121 -> 109612.57 | M52: =M121 -> 113235.82 | N52: =N121 -> 116579.14 | O52: =O121 -> 120170.55 | ... Q52: =Q121 -> 127005.78
B53: Goodwill & Intangibles | C53: =SUM('Data Sheet'!C46:C48) -> 11724.2 | D53: =SUM('Data Sheet'!D46:D48) -> 11913.84 | E53: =SUM('Data Sheet'!E46:E48) -> 11863.66 | F53: =SUM('Data Sheet'!F46:F48) -> 17759.22 | G53: =SUM('Data Sheet'!G46:G48) -> 18262.23 | H53: =G53 -> 18262.23 | I53: =H53 -> 18262.23 | J53: =I53 -> 18262.23 | K53: =J53 -> 18262.23 | L53: =K53 -> 18262.23 | M53: =L53 -> 18262.23 | N53: =M53 -> 18262.23 | O53: =N53 -> 18262.23 | ... Q53: =P53 -> 18262.23
B54: Financial Assets | C54: =SUM('Data Sheet'!C52:C54,'Data Sheet'!C63,'Data Sheet'!C67:C68,'Data Sheet'!C73) -> 9313.51 | D54: =SUM('Data Sheet'!D52:D54,'Data Sheet'!D63,'Data Sheet'!D67:D68,'Data Sheet'!D73) -> 9770.78 | E54: =SUM('Data Sheet'!E52:E54,'Data Sheet'!E63,'Data Sheet'!E67:E68,'Data Sheet'!E73) -> 11079.71 | F54: =SUM('Data Sheet'!F52:F54,'Data Sheet'!F63,'Data Sheet'!F67:F68,'Data Sheet'!F73) -> 9252.09 | G54: =SUM('Data Sheet'!G52:G54,'Data Sheet'!G63,'Data Sheet'!G67:G68,'Data Sheet'!G73) -> 11195.63 | H54: =G54 -> 11195.63 | I54: =H54 -> 11195.63 | J54: =I54 -> 11195.63 | K54: =J54 -> 11195.63 | L54: =K54 -> 11195.63 | M54: =L54 -> 11195.63 | N54: =M54 -> 11195.63 | O54: =N54 -> 11195.63 | ... Q54: =P54 -> 11195.63
B55: Investment in associates and joint venture | C55: ='Data Sheet'!C50 -> 30.17 | D55: ='Data Sheet'!D50 -> 876.01 | E55: ='Data Sheet'!E50 -> 968.94 | F55: ='Data Sheet'!F50 -> 300.12 | G55: ='Data Sheet'!G50 -> 319.41 | H55: =G55 -> 319.41 | I55: =H55 -> 319.41 | J55: =I55 -> 319.41 | K55: =J55 -> 319.41 | L55: =K55 -> 319.41 | M55: =L55 -> 319.41 | N55: =M55 -> 319.41 | O55: =N55 -> 319.41 | ... Q55: =P55 -> 319.41
B56: Other non current assets | C56: =SUM('Data Sheet'!C56:C58,'Data Sheet'!C70) -> 3574.17 | D56: =SUM('Data Sheet'!D56:D58,'Data Sheet'!D70) -> 3674.06 | E56: =SUM('Data Sheet'!E56:E58,'Data Sheet'!E70) -> 3725.23 | F56: =SUM('Data Sheet'!F56:F58,'Data Sheet'!F70) -> 3972.77 | G56: =SUM('Data Sheet'!G56:G58,'Data Sheet'!G70) -> 2572.75 | H56: =G56 -> 2572.75 | I56: =H56 -> 2572.75 | J56: =I56 -> 2572.75 | K56: =J56 -> 2572.75 | L56: =K56 -> 2572.75 | M56: =L56 -> 2572.75 | N56: =M56 -> 2572.75 | O56: =N56 -> 2572.75 | ... Q56: =P56 -> 2572.75
B57: Total Assets | C57: =SUM(C45:C56) -> 83827.79 | D57: =SUM(D45:D56) -> 91386.96 | E57: =SUM(E45:E56) -> 100802.01 | F57: =SUM(F45:F56) -> 133697.15 | G57: =SUM(G45:G56) -> 141376.05 | H57: =SUM(H45:H56) -> 148659.55 | I57: =SUM(I45:I56) -> 156682.1 | J57: =SUM(J45:J56) -> 164595.48 | ... Q57: =SUM(Q45:Q56) -> 257364.72
B59: Current Liabilities
B60: Account Paybles | C60: =SUM('Data Sheet'!C98:C99) -> 5862.83 | D60: =SUM('Data Sheet'!D98:D99) -> 7209.3 | E60: =SUM('Data Sheet'!E98:E99) -> 8478.33 | F60: =SUM('Data Sheet'!F98:F99) -> 9327.48 | G60: =SUM('Data Sheet'!G98:G99) -> 10236.71 | H60: =-H8*H38/365 -> 10937.534 | I60: =-I8*I38/365 -> 12238.212 | J60: =-J8*J38/365 -> 13746.729 | K60: =-K8*K38/365 -> 15118.965 | L60: =-L8*L38/365 -> 16610.975 | M60: =-M8*M38/365 -> 18135.068 | N60: =-N8*N38/365 -> 19505.876 | O60: =-O8*O38/365 -> 20899.139 | ... Q60: =-Q8*Q38/365 -> 23786.8
B61: Other current liability | C61: =SUM('Data Sheet'!C101:C105) -> 9274.76 | D61: =SUM('Data Sheet'!D101:D105) -> 11531.81 | E61: =SUM('Data Sheet'!E101:E105) -> 13274.57 | F61: =SUM('Data Sheet'!F101:F105) -> 15584.29 | G61: =SUM('Data Sheet'!G101:G105) -> 15610.44 | H61: =G61 -> 15610.44 | I61: =H61 -> 15610.44 | J61: =I61 -> 15610.44 | K61: =J61 -> 15610.44 | L61: =K61 -> 15610.44 | M61: =L61 -> 15610.44 | N61: =M61 -> 15610.44 | O61: =N61 -> 15610.44 | ... Q61: =P61 -> 15610.44
B63: Non current liability
B64: Debt (incl. lease liabilities) | C64: =SUM('Data Sheet'!C85:C86,'Data Sheet'!C95:C96) -> 11298.8 | D64: =SUM('Data Sheet'!D85:D86,'Data Sheet'!D95:D96) -> 11057.74 | E64: =SUM('Data Sheet'!E85:E86,'Data Sheet'!E95:E96) -> 11402.95 | F64: =SUM('Data Sheet'!F85:F86,'Data Sheet'!F95:F96) -> 24102.18 | G64: =SUM('Data Sheet'!G85:G86,'Data Sheet'!G95:G96) -> 23755.09 | H64: =H126 -> 23755.09 | I64: =I126 -> 22755.09 | J64: =J126 -> 20255.09 | K64: =K126 -> 17755.09 | L64: =L126 -> 15255.09 | M64: =M126 -> 12755.09 | N64: =N126 -> 10755.09 | O64: =O126 -> 8755.09 | ... Q64: =Q126 -> 5755.09
B65: Other non current liability | C65: =SUM('Data Sheet'!C87:C89,'Data Sheet'!C91) -> 925.95 | D65: =SUM('Data Sheet'!D87:D89,'Data Sheet'!D91) -> 947.83 | E65: =SUM('Data Sheet'!E87:E89,'Data Sheet'!E91) -> 914.96 | F65: =SUM('Data Sheet'!F87:F89,'Data Sheet'!F91) -> 1210.4 | G65: =SUM('Data Sheet'!G87:G89,'Data Sheet'!G91) -> 1171.31 | H65: =G65 -> 1171.31 | I65: =H65 -> 1171.31 | J65: =I65 -> 1171.31 | K65: =J65 -> 1171.31 | L65: =K65 -> 1171.31 | M65: =L65 -> 1171.31 | N65: =M65 -> 1171.31 | O65: =N65 -> 1171.31 | ... Q65: =P65 -> 1171.31
B66: Deferred Tax Liability | C66: ='Data Sheet'!C90 -> 6033.24 | D66: ='Data Sheet'!D90 -> 6260.11 | E66: ='Data Sheet'!E90 -> 6447.78 | F66: ='Data Sheet'!F90 -> 9579.44 | G66: ='Data Sheet'!G90 -> 9890.06 | H66: =G66 -> 9890.06 | I66: =H66 -> 9890.06 | J66: =I66 -> 9890.06 | K66: =J66 -> 9890.06 | L66: =K66 -> 9890.06 | M66: =L66 -> 9890.06 | N66: =M66 -> 9890.06 | O66: =N66 -> 9890.06 | ... Q66: =P66 -> 9890.06
B67: Total Liabilities | C67: =SUM(C60:C66) -> 33395.58 | D67: =SUM(D60:D66) -> 37006.79 | E67: =SUM(E60:E66) -> 40518.59 | F67: =SUM(F60:F66) -> 59803.79 | G67: =SUM(G60:G66) -> 60663.61 | H67: =SUM(H60:H66) -> 61364.434 | I67: =SUM(I60:I66) -> 61665.112 | J67: =SUM(J60:J66) -> 60673.629 | ... Q67: =SUM(Q60:Q66) -> 56213.7
B69: Shareholder's Equity
B70: Equity Share Capital | C70: ='Data Sheet'!C77 -> 288.67 | D70: ='Data Sheet'!D77 -> 288.69 | E70: ='Data Sheet'!E77 -> 288.69 | F70: ='Data Sheet'!F77 -> 294.68 | G70: ='Data Sheet'!G77 -> 294.68 | H70: =G70 -> 294.68 | I70: =H70 -> 294.68 | J70: =I70 -> 294.68 | K70: =J70 -> 294.68 | L70: =K70 -> 294.68 | M70: =L70 -> 294.68 | N70: =M70 -> 294.68 | O70: =N70 -> 294.68 | ... Q70: =P70 -> 294.68
B71: Retained Earnings | C71: ='Data Sheet'!C78 -> 50146.6 | D71: ='Data Sheet'!D78 -> 54035.85 | E71: ='Data Sheet'!E78 -> 59938.78 | F71: ='Data Sheet'!F78 -> 70411.53 | G71: ='Data Sheet'!G78 -> 76328.86 | H71: =G71+H22+H99 -> 82886.265 | I71: =H71+I22+I99 -> 90578.486 | J71: =I71+J22+J99 -> 99449.156 | K71: =J71+K22+K99 -> 109572.17 | L71: =K71+L22+L99 -> 120982.94 | M71: =L71+M22+M99 -> 133731.14 | N71: =M71+N22+N99 -> 147635.65 | O71: =N71+O22+O99 -> 162697.27 | ... Q71: =P71+Q22+Q99 -> 196305.02
B72: Shareholder's Equity | C72: =SUM(C70:C71) -> 50435.27 | D72: =SUM(D70:D71) -> 54324.54 | E72: =SUM(E70:E71) -> 60227.47 | F72: =SUM(F70:F71) -> 70706.21 | G72: =SUM(G70:G71) -> 76623.54 | H72: =SUM(H70:H71) -> 83180.945 | I72: =SUM(I70:I71) -> 90873.166 | J72: =SUM(J70:J71) -> 99743.836 | ... Q72: =SUM(Q70:Q71) -> 196599.7
B73: Non Controlling Interest | C73: ='Data Sheet'!C79 -> -3.06 | D73: ='Data Sheet'!D79 -> 55.63 | E73: ='Data Sheet'!E79 -> 55.94 | F73: ='Data Sheet'!F79 -> 3186.59 | G73: ='Data Sheet'!G79 -> 4088.9 | H73: =G73-H21 -> 4114.1735 | I73: =H73-I21 -> 4143.8208 | J73: =I73-J21 -> 4178.0101 | K73: =J73-K21 -> 4217.0262 | L73: =K73-L21 -> 4261.0056 | M73: =L73-M21 -> 4310.1396 | N73: =M73-N21 -> 4363.7303 | O73: =N73-O21 -> 4421.7807 | ... Q73: =P73-Q21 -> 4551.3116
B74: Total Equity & Liability | C74: =C67+C72+C73+'Data Sheet'!C81 -> 83827.79 | D74: =D67+D72+D73+'Data Sheet'!D81 -> 91386.96 | E74: =E67+E72+E73+'Data Sheet'!E81 -> 100802.01 | F74: =F67+F72+F73+'Data Sheet'!F81 -> 133697.15 | G74: =G67+G72+G73+'Data Sheet'!G81 -> 141376.05 | H74: =H67+H72+H73 -> 148659.55 | I74: =I67+I72+I73 -> 156682.1 | J74: =J67+J72+J73 -> 164595.48 | K74: =K67+K72+K73 -> 173629.74 | L74: =L67+L72+L73 -> 184076.5 | M74: =M67+M72+M73 -> 195897.93 | N74: =N67+N72+N73 -> 209226.84 | O74: =O67+O72+O73 -> 223739.77 | ... Q74: =Q67+Q72+Q73 -> 257364.72
B76: Balance Check | C76: =IF((C57-C74)<0.01, "Correct",C57-C74) -> Correct | D76: =IF((D57-D74)<0.01, "Correct",D57-D74) -> Correct | E76: =IF((E57-E74)<0.01, "Correct",E57-E74) -> Correct | F76: =IF((F57-F74)<0.01, "Correct",F57-F74) -> Correct | G76: =IF((G57-G74)<0.01, "Correct",G57-G74) -> Correct | H76: =IF((H57-H74)<0.01, "Correct",H57-H74) -> Correct | I76: =IF((I57-I74)<0.01, "Correct",I57-I74) -> Correct | J76: =IF((J57-J74)<0.01, "Correct",J57-J74) -> Correct | ... Q76: =IF((Q57-Q74)<0.01, "Correct",Q57-Q74) -> Correct
A78: # | B78: Cash Flow Statement
B80: Cash from operating activities
B81: Net Income | C81: =C19 -> 7174.34 | D81: =D19 -> 5073.4 | E81: =E19 -> 7003.96 | F81: =F19 -> 6039.64 | G81: =G19 -> 8188.35 | H81: =H19 -> 9112.6574 | I81: =I19 -> 10689.682 | J81: =J19 -> 12327.342 | ... Q81: =Q19 -> 24158.482
B82: Tax charge on p&l but not paid in cash | C82: =-C18+'Data Sheet'!C137 -> -364.83 | D82: =-D18+'Data Sheet'!D137 -> 1218.54 | E82: =-E18+'Data Sheet'!E137 -> 767.74 | F82: =-F18+'Data Sheet'!F137 -> 187.86 | G82: =-G18+'Data Sheet'!G137 -> 1438.15 | H82: 0 | I82: 0 | J82: 0 | K82: 0 | L82: 0 | M82: 0 | N82: 0 | O82: 0 | P82: 0 | Q82: 0
B83: Depreciation & Amortization | C83: =-C13 -> 2714.75 | D83: =-D13 -> 2887.99 | E83: =-E13 -> 3145.3 | F83: =-F13 -> 4014.95 | G83: =-G13 -> 4644.46 | H83: =-H13 -> 4993.1559 | I83: =-I13 -> 5269.748 | J83: =-J13 -> 5558.4535 | ... Q83: =-Q13 -> 6905.2107
B84: Add/Less: Adjustment for non operating items | C84: =SUM('Data Sheet'!C115:C128) -> 232 | D84: =SUM('Data Sheet'!D115:D128) -> 225.53 | E84: =SUM('Data Sheet'!E115:E128) -> 461.59 | F84: =SUM('Data Sheet'!F115:F128) -> 1102.05 | G84: =SUM('Data Sheet'!G115:G128) -> 1278.07 | H84: =-H15-H16 -> 1394.8085 | I84: =-I15-I16 -> 1334.2945 | J84: =-J15-J16 -> 1194.5614 | K84: =-K15-K16 -> 938.90161 | L84: =-L15-L16 -> 680.57554 | M84: =-M15-M16 -> 419.53883 | N84: =-N15-N16 -> 165.77354 | O84: =-O15-O16 -> -50.235891 | ... Q84: =-Q15-Q16 -> -447.14674
B85: Add/Less: Adjustment for Working Capital Changes | C85: =SUM('Data Sheet'!C131:C135) -> -473.02 | D85: =SUM('Data Sheet'!D131:D135) -> -336.95 | E85: =SUM('Data Sheet'!E131:E135) -> -481.05 | F85: =SUM('Data Sheet'!F131:F135) -> -671.07 | G85: =SUM('Data Sheet'!G131:G135) -> -233.17 | H85: =H114 -> -963.48931 | I85: =I114 -> -790.2672 | J85: =J114 -> -879.29872 | K85: =K114 -> -817.70178 | L85: =L114 -> -877.99051 | M85: =M114 -> -902.7151 | N85: =N114 -> -808.98153 | O85: =O114 -> -823.95502 | ... Q85: =Q114 -> -861.78453
B86: Cash From Operating Activities | C86: =SUM(C81:C85) -> 9283.24 | D86: =SUM(D81:D85) -> 9068.51 | E86: =SUM(E81:E85) -> 10897.54 | F86: =SUM(F81:F85) -> 10673.43 | G86: =SUM(G81:G85) -> 15315.86 | H86: =SUM(H81:H85) -> 14537.132 | I86: =SUM(I81:I85) -> 16503.457 | J86: =SUM(J81:J85) -> 18201.058 | ... Q86: =SUM(Q81:Q85) -> 29754.761
B88: Cash From Investing Activities
B89: Purchase of PP&E | C89: ='Data Sheet'!C140 -> -5613.41 | D89: ='Data Sheet'!D140 -> -6200.11 | E89: ='Data Sheet'!E140 -> -9005.59 | F89: ='Data Sheet'!F140 -> -9129.33 | G89: ='Data Sheet'!G140 -> -9677.77 | H89: =-H118 -> -9938.3999 | I89: =-I118 -> -10431.569 | J89: =-J118 -> -8871.6632 | K89: =-K118 -> -9315.819 | L89: =-L118 -> -9290.2035 | M89: =-M118 -> -9753.9876 | N89: =-N118 -> -9676.6981 | O89: =-O118 -> -10111.797 | ... Q89: =-Q118 -> -10451.409
B90: Sale of PP&E | C90: ='Data Sheet'!C141 -> 73.44 | D90: ='Data Sheet'!D141 -> 94.53 | E90: ='Data Sheet'!E141 -> 121.54 | F90: ='Data Sheet'!F141 -> 178.7 | G90: ='Data Sheet'!G141 -> 167.16 | H90: 0 | I90: 0 | J90: 0 | K90: 0 | L90: 0 | M90: 0 | N90: 0 | O90: 0 | P90: 0 | Q90: 0
B91: Purchases / sale of investments | C91: =SUM('Data Sheet'!C142:C151) -> 7622.61 | D91: =SUM('Data Sheet'!D142:D151) -> -1364.23 | E91: =SUM('Data Sheet'!E142:E151) -> -65.47 | F91: =SUM('Data Sheet'!F142:F151) -> -7896.67 | G91: =SUM('Data Sheet'!G142:G151) -> -176.8 | H91: =G54-H54 -> 0 | I91: =H54-I54 -> 0 | J91: =I54-J54 -> 0 | K91: =J54-K54 -> 0 | L91: =K54-L54 -> 0 | M91: =L54-M54 -> 0 | N91: =M54-N54 -> 0 | O91: =N54-O54 -> 0 | ... Q91: =P54-Q54 -> 0
B92: Dividend Received | C92: ='Data Sheet'!C152 -> 0 | D92: ='Data Sheet'!D152 -> 0 | E92: ='Data Sheet'!E152 -> 0.16 | F92: ='Data Sheet'!F152 -> 0.81 | G92: ='Data Sheet'!G152 -> 0 | H92: 0 | I92: 0 | J92: 0 | K92: 0 | L92: 0 | M92: 0 | N92: 0 | O92: 0 | P92: 0 | Q92: 0
B93: Interest Received | C93: ='Data Sheet'!C153 -> 174.37 | D93: ='Data Sheet'!D153 -> 282.74 | E93: ='Data Sheet'!E153 -> 161.24 | F93: ='Data Sheet'!F153 -> 342.03 | G93: ='Data Sheet'!G153 -> 207.33 | H93: =H16 -> 463.32672 | I93: =I16 -> 523.84068 | J93: =J16 -> 585.35332 | K93: =K16 -> 645.46183 | L93: =L16 -> 708.23663 | M93: =M16 -> 773.72206 | N93: =N16 -> 831.93609 | O93: =O16 -> 891.5045 | ... Q93: =Q16 -> 1014.6436
B94: Cash From Investing Activities | C94: =SUM(C89:C93) -> 2257.01 | D94: =SUM(D89:D93) -> -7187.07 | E94: =SUM(E89:E93) -> -8788.12 | F94: =SUM(F89:F93) -> -16504.46 | G94: =SUM(G89:G93) -> -9480.08 | H94: =SUM(H89:H93) -> -9475.0731 | I94: =SUM(I89:I93) -> -9907.7288 | J94: =SUM(J89:J93) -> -8286.3099 | ... Q94: =SUM(Q89:Q93) -> -9436.7653
B96: Cash From Financing Activities
B97: Issuance/Repayment of Debt | C97: =SUM('Data Sheet'!C159:C162) -> -10328.59 | D97: =SUM('Data Sheet'!D159:D162) -> 326.96 | E97: =SUM('Data Sheet'!E159:E162) -> 167.92 | F97: =SUM('Data Sheet'!F159:F162) -> 8694.16 | G97: =SUM('Data Sheet'!G159:G162) -> -1682.42 | H97: =H125 -> 0 | I97: =I125 -> -1000 | J97: =J125 -> -2500 | K97: =K125 -> -2500 | L97: =L125 -> -2500 | M97: =M125 -> -2500 | N97: =N125 -> -2000 | O97: =O125 -> -2000 | ... Q97: =Q125 -> -1500
B98: Net Issuance/(Purchase) of Equity & Treasury Shares | C98: =SUM('Data Sheet'!C156:C158) -> -78.16 | D98: =SUM('Data Sheet'!D156:D158) -> -101.75 | E98: =SUM('Data Sheet'!E156:E158) -> -82.46 | F98: =SUM('Data Sheet'!F156:F158) -> -66.98 | G98: =SUM('Data Sheet'!G156:G158) -> -69.34 | H98: 0 | I98: 0 | J98: 0 | K98: 0 | L98: 0 | M98: 0 | N98: 0 | O98: 0 | P98: 0 | Q98: 0
B99: Dividend Paid | C99: ='Data Sheet'!C165 -> -1065 | D99: ='Data Sheet'!D165 -> -1091.27 | E99: ='Data Sheet'!E165 -> -1094.43 | F99: ='Data Sheet'!F165 -> -2011.65 | G99: ='Data Sheet'!G165 -> -2273.36 | H99: =-H22*H35 -> -2529.9787 | I99: =-I22*I35 -> -2967.8134 | J99: =-J22*J35 -> -3422.4827 | K99: =-K22*K35 -> -3905.6608 | L99: =-L22*L35 -> -4402.5058 | M99: =-M22*M35 -> -4918.5125 | N99: =-N22*N35 -> -5364.6379 | O99: =-O22*O35 -> -5811.0755 | ... Q99: =-Q22*Q35 -> -6707.203
B100: Interest Paid | C100: =SUM('Data Sheet'!C163:C164) -> -1026.18 | D100: =SUM('Data Sheet'!D163:D164) -> -764.94 | E100: =SUM('Data Sheet'!E163:E164) -> -916.68 | F100: =SUM('Data Sheet'!F163:F164) -> -1539.77 | G100: =SUM('Data Sheet'!G163:G164) -> -1928.45 | H100: =H127 -> -1858.1352 | I100: =I127 -> -1858.1352 | J100: =J127 -> -1779.9147 | K100: =K127 -> -1584.3634 | L100: =L127 -> -1388.8122 | M100: =M127 -> -1193.2609 | N100: =N127 -> -997.70963 | O100: =O127 -> -841.26861 | ... Q100: =Q127 -> -567.49683
B101: Cash From Financing Activities | C101: =SUM(C97:C100) -> -12497.93 | D101: =SUM(D97:D100) -> -1631 | E101: =SUM(E97:E100) -> -1925.65 | F101: =SUM(F97:F100) -> 5075.76 | G101: =SUM(G97:G100) -> -5953.57 | H101: =SUM(H97:H100) -> -4388.1139 | I101: =SUM(I97:I100) -> -5825.9486 | J101: =SUM(J97:J100) -> -7702.3974 | ... Q101: =SUM(Q97:Q100) -> -8774.6998
B103: Net change in cash | C103: =C86+C94+C101 -> -957.68 | D103: =D86+D94+D101 -> 250.44 | E103: =E86+E94+E101 -> 183.77 | F103: =F86+F94+F101 -> -755.27 | G103: =G86+G94+G101 -> -117.79 | H103: =H86+H94+H101 -> 673.94544 | I103: =I86+I94+I101 -> 769.77967 | J103: =J86+J94+J101 -> 2212.351 | ... Q103: =Q86+Q94+Q101 -> 11543.296
B104: Add: Cash at beginning of period | C104: =SUM('Data Sheet'!C168:C169) -> 1078.22 | D104: =SUM('Data Sheet'!D168:D169) -> 119.93 | E104: =SUM('Data Sheet'!E168:E169) -> 369.81 | F104: =SUM('Data Sheet'!F168:F169) -> 1222.47 | G104: =SUM('Data Sheet'!G168:G169) -> 472.27 | H104: =G45 -> 354.48 | I104: =H45 -> 1028.4254 | J104: =I45 -> 1798.2051 | K104: =J45 -> 4010.5561 | L104: =K45 -> 7282.8262 | M104: =L45 -> 12012.938 | N104: =M45 -> 17784.306 | O104: =N45 -> 25590.11 | ... Q104: =P45 -> 44946.829
B105: Cash at end of period | C105: =SUM(C103:C104) -> 120.54 | D105: =SUM(D103:D104) -> 370.37 | E105: =SUM(E103:E104) -> 553.58 | F105: =SUM(F103:F104) -> 467.2 | G105: =SUM(G103:G104) -> 354.48 | H105: =SUM(H103:H104) -> 1028.4254 | I105: =SUM(I103:I104) -> 1798.2051 | J105: =SUM(J103:J104) -> 4010.5561 | ... Q105: =SUM(Q103:Q104) -> 56490.125
A107: # | B107: Supporting Schedules
B109: Working Capital
B110: Accounts Receivables | C110: ='Data Sheet'!C133 -> -495.26 | D110: ='Data Sheet'!D133 -> -752.33 | E110: ='Data Sheet'!E133 -> -420.96 | F110: ='Data Sheet'!F133 -> -607.54 | G110: ='Data Sheet'!G133 -> -27.6 | H110: =G47-H47 -> -477.83635 | I110: =H47-I47 -> -860.58231 | J110: =I47-J47 -> -859.07984 | K110: =J47-K47 -> -848.05212 | L110: =K47-L47 -> -880.70618 | M110: =L47-M47 -> -921.46074 | N110: =M47-N47 -> -817.79913 | O110: =N47-O47 -> -837.62116 | ... Q110: =P47-Q47 -> -874.84837
B111: Inventories | C111: ='Data Sheet'!C134 -> -1578.96 | D111: ='Data Sheet'!D134 -> -991.91 | E111: ='Data Sheet'!E134 -> -1711.53 | F111: ='Data Sheet'!F134 -> -316.93 | G111: ='Data Sheet'!G134 -> -67.92 | H111: =G48-H48 -> -1186.4767 | I111: =H48-I48 -> -1230.3633 | J111: =I48-J48 -> -1528.7353 | K111: =J48-K48 -> -1341.8859 | L111: =K48-L48 -> -1489.2949 | M111: =L48-M48 -> -1505.3471 | N111: =M48-N48 -> -1361.9905 | O111: =N48-O48 -> -1379.597 | ... Q111: =P48-Q48 -> -1444.9326
B112: Accounts Paybles | C112: ='Data Sheet'!C131 -> 2076.9 | D112: ='Data Sheet'!D131 -> 1868.6 | E112: ='Data Sheet'!E131 -> 1959 | F112: ='Data Sheet'!F131 -> -475.55 | G112: ='Data Sheet'!G131 -> 590.28 | H112: =H60-G60 -> 700.82373 | I112: =I60-H60 -> 1300.6784 | J112: =J60-I60 -> 1508.5164 | K112: =K60-J60 -> 1372.2362 | L112: =L60-K60 -> 1492.0106 | M112: =M60-L60 -> 1524.0928 | N112: =N60-M60 -> 1370.8081 | O112: =O60-N60 -> 1393.2631 | ... Q112: =Q60-P60 -> 1457.9965
B113: Other Adjustments | C113: =SUM('Data Sheet'!C132,'Data Sheet'!C135) -> -475.7 | D113: =SUM('Data Sheet'!D132,'Data Sheet'!D135) -> -461.31 | E113: =SUM('Data Sheet'!E132,'Data Sheet'!E135) -> -307.56 | F113: =SUM('Data Sheet'!F132,'Data Sheet'!F135) -> 728.95 | G113: =SUM('Data Sheet'!G132,'Data Sheet'!G135) -> -727.93 | H113: =G49-H49+H61-G61 -> 0 | I113: =H49-I49+I61-H61 -> 0 | J113: =I49-J49+J61-I61 -> 0 | K113: =J49-K49+K61-J61 -> 0 | L113: =K49-L49+L61-K61 -> 0 | M113: =L49-M49+M61-L61 -> 0 | N113: =M49-N49+N61-M61 -> 0 | O113: =N49-O49+O61-N61 -> 0 | ... Q113: =P49-Q49+Q61-P61 -> 0
B114: Total | C114: =SUM(C110:C113) -> -473.02 | D114: =SUM(D110:D113) -> -336.95 | E114: =SUM(E110:E113) -> -481.05 | F114: =SUM(F110:F113) -> -671.07 | G114: =SUM(G110:G113) -> -233.17 | H114: =SUM(H110:H113) -> -963.48931 | I114: =SUM(I110:I113) -> -790.2672 | J114: =SUM(J110:J113) -> -879.29872 | ... Q114: =SUM(Q110:Q113) -> -861.78453
B116: Property Plant & Equipment
B117: Beginning of period | D117: =C121 -> 48548.04 | E117: =D121 -> 51705.55 | F117: =E121 -> 57825.13 | G117: =F121 -> 83039.19 | H117: =G121 -> 89273.59 | I117: =H121 -> 94218.834 | J117: =I121 -> 99380.655 | K117: =J121 -> 102693.87 | ... Q117: =P121 -> 123459.59
B118: Add: Capex | D118: =-'Data Sheet'!D140 -> 6200.11 | E118: =-'Data Sheet'!E140 -> 9005.59 | F118: =-'Data Sheet'!F140 -> 9129.33 | G118: =-'Data Sheet'!G140 -> 9677.77 | H118: =(H149-H168)*H165+H7*H167 -> 9938.3999 | I118: =(I149-I168)*I165+I7*I167 -> 10431.569 | J118: =(J149-J168)*J165+J7*J167 -> 8871.6632 | K118: =(K149-K168)*K165+K7*K167 -> 9315.819 | L118: =(L149-L168)*L165+L7*L167 -> 9290.2035 | M118: =(M149-M168)*M165+M7*M167 -> 9753.9876 | N118: =(N149-N168)*N165+N7*N167 -> 9676.6981 | O118: =(O149-O168)*O165+O7*O167 -> 10111.797 | ... Q118: =(Q149-Q168)*Q165+Q7*Q167 -> 10451.409
B119: Add: Acquisition , leases and other | D119: =D121-D117-D118-D120 -> -154.61 | E119: =E121-E117-E118-E120 -> 259.29 | F119: =F121-F117-F118-F120 -> 20099.68 | G119: =G121-G117-G118-G120 -> 1201.09 | H119: 0 | I119: 0 | J119: 0 | K119: 0 | L119: 0 | M119: 0 | N119: 0 | O119: 0 | P119: 0 | Q119: 0
B120: Less: Depreciation | D120: =D13 -> -2887.99 | E120: =E13 -> -3145.3 | F120: =F13 -> -4014.95 | G120: =G13 -> -4644.46 | H120: =-H31*H117 -> -4993.1559 | I120: =-I31*I117 -> -5269.748 | J120: =-J31*J117 -> -5558.4535 | K120: =-K31*K117 -> -5743.7645 | L120: =-L31*L117 -> -5943.5528 | M120: =-M31*M117 -> -6130.7342 | N120: =-N31*N117 -> -6333.3861 | O120: =-O31*O117 -> -6520.3807 | ... Q120: =-Q31*Q117 -> -6905.2107
...

Sheet Comps Data
B2: S.No. | C2: Company | D2: CMP Rs. | E2: No. Eq. Shares Cr. | F2: Debt Rs.Cr. | G2: Cash Rs.Cr. | H2: Sales Rs.Cr. | I2: EBITDA | J2: NP Ann Rs.Cr. | K2: Tax Rate
B3: 1 | C3: UltraTech Cem. | D3: 10675 | E3: 29.47 | F3: 23755.09 | G3: 1384.35 | H3: 88511.53 | I3: 17004.4 | J3: 8188.35 | K3: 0.2464
B4: 2 | C4: Ambuja Cements | D4: 350 | E4: 248.48 | F4: 865.93 | G4: 958.6 | H4: 40655.68 | I4: 6576.88 | J4: 5637.08 | K4: 0.2705
B5: 3 | C5: Shree Cement | D5: 22145 | E5: 3.61 | F5: 1868.14 | G5: 341.79 | H5: 20943.47 | I5: 4637.86 | J5: 1748.66 | K5: 0.2592
B6: 4 | C6: J K Cements | D6: 4851 | E6: 7.73 | F6: 6182.99 | G6: 469.11 | H6: 13722.3 | I6: 2378.71 | J6: 987.99 | K6: 0.3374
B7: 5 | C7: Dalmia Bharat Ltd | D7: 1598.6 | E7: 18.76 | F7: 7406 | G7: 224 | H7: 14804 | I7: 3083 | J7: 1157 | K7: 0.2375
B8: 6 | C8: ACC | D8: 1136 | E8: 18.78 | F8: 428.61 | G8: 557.73 | H8: 25961.85 | I8: 2957.97 | J8: 2137.23 | K8: 0.2577
B9: 7 | C9: The Ramco Cement | D9: 809.4 | E9: 23.63 | F9: 3871.1 | G9: 227.29 | H9: 9028.76 | I9: 1437.39 | J9: 698.79 | K9: 0.2508

Sheet Ratio Analysis
B2: =Model!B2 -> UltraTech Cement Ltd
B3: Ratio Analysis | C3: 2022 | D3: =C3+1 -> 2023 | E3: =D3+1 -> 2024 | F3: =E3+1 -> 2025 | G3: =F3+1 -> 2026 | H3: =G3+1 -> 2027 | I3: =H3+1 -> 2028 | J3: =I3+1 -> 2029 | K3: =J3+1 -> 2030 | ... Q3: =P3+1 -> 2036
B5: Profitability Ratios
B6: Gross Margin | C6: =Model!C9/Model!C7 -> 0.61781945 | D6: =Model!D9/Model!D7 -> 0.55398025 | E6: =Model!E9/Model!E7 -> 0.57429091 | F6: =Model!F9/Model!F7 -> 0.57708084 | G6: =Model!G9/Model!G7 -> 0.58439855 | H6: =Model!H9/Model!H7 -> 0.58439855 | I6: =Model!I9/Model!I7 -> 0.58439855 | J6: =Model!J9/Model!J7 -> 0.58439855 | ... Q6: =Model!Q9/Model!Q7 -> 0.58439855
B7: EBITDA Margin | C7: =Model!C12/Model!C7 -> 0.21890886 | D7: =Model!D12/Model!D7 -> 0.16792937 | E7: =Model!E12/Model!E7 -> 0.1828924 | F7: =Model!F12/Model!F7 -> 0.16532721 | G7: =Model!G12/Model!G7 -> 0.19229393 | H7: =Model!H12/Model!H7 -> 0.19138078 | I7: =Model!I12/Model!I7 -> 0.1904499 | J7: =Model!J12/Model!J7 -> 0.18950095 | ... Q7: =Model!Q12/Model!Q7 -> 0.18232181
B8: EBIT Margin | C8: =Model!C14/Model!C7 -> 0.1672965 | D8: =Model!D14/Model!D7 -> 0.12226221 | E8: =Model!E14/Model!E7 -> 0.13853501 | F8: =Model!F14/Model!F7 -> 0.11246772 | G8: =Model!G14/Model!G7 -> 0.13982099 | H8: =Model!H14/Model!H7 -> 0.13986246 | I8: =Model!I14/Model!I7 -> 0.14235882 | J8: =Model!J14/Model!J7 -> 0.14410576 | ... Q8: =Model!Q14/Model!Q7 -> 0.14978781
B9: Pre Tax Margin | C9: =Model!C17/Model!C7 -> 0.15902255 | D9: =Model!D17/Model!D7 -> 0.11727154 | E9: =Model!E17/Model!E7 -> 0.13287924 | F9: =Model!F17/Model!F7 -> 0.099112858 | G9: =Model!G17/Model!G7 -> 0.12345499 | H9: =Model!H17/Model!H7 -> 0.12547112 | I9: =Model!I17/Model!I7 -> 0.13018221 | J9: =Model!J17/Model!J7 -> 0.13434993 | ... Q9: =Model!Q17/Model!Q7 -> 0.15189455
B10: Effective Tax Rate | C10: =-Model!C18/Model!C17 -> 0.14227679 | D10: =-Model!D18/Model!D17 -> 0.31590764 | E10: =-Model!E18/Model!E17 -> 0.25665501 | F10: =-Model!F18/Model!F17 -> 0.19772374 | G10: =-Model!G18/Model!G17 -> 0.25064449 | H10: =-Model!H18/Model!H17 -> 0.25064449 | I10: =-Model!I18/Model!I17 -> 0.25064449 | J10: =-Model!J18/Model!J17 -> 0.25064449 | ... Q10: =-Model!Q18/Model!Q17 -> 0.25064449
B11: ROIC | C11: =Model!C14*(1-Model!C34)/(Model!C72+Model!C64-Model!C45-Model!C46) -> 0.12297572 | D11: =Model!D14*(1-Model!D34)/(Model!D72+Model!D64-Model!D45-Model!D46) -> 0.08234602 | E11: =Model!E14*(1-Model!E34)/(Model!E72+Model!E64-Model!E45-Model!E46) -> 0.10306787 | F11: =Model!F14*(1-Model!F34)/(Model!F72+Model!F64-Model!F45-Model!F46) -> 0.073586083 | G11: =Model!G14*(1-Model!G34)/(Model!G72+Model!G64-Model!G45-Model!G46) -> 0.093680679 | H11: =Model!H14*(1-Model!H34)/(Model!H72+Model!H64-Model!H45-Model!H46) -> 0.096854346 | I11: =Model!I14*(1-Model!I34)/(Model!I72+Model!I64-Model!I45-Model!I46) -> 0.10550112 | J11: =Model!J14*(1-Model!J34)/(Model!J72+Model!J64-Model!J45-Model!J46) -> 0.11501971 | ... Q11: =Model!Q14*(1-Model!Q34)/(Model!Q72+Model!Q64-Model!Q45-Model!Q46) -> 0.16448678
B12: Net Margin | C12: =Model!C19/Model!C7 -> 0.13639733 | D12: =Model!D19/Model!D7 -> 0.080224567 | E12: =Model!E19/Model!E7 -> 0.098775119 | F12: =Model!F19/Model!F7 -> 0.079515893 | G12: =Model!G19/Model!G7 -> 0.092511676 | H12: =Model!H19/Model!H7 -> 0.094022473 | I12: =Model!I19/Model!I7 -> 0.097552752 | J12: =Model!J19/Model!J7 -> 0.10067586 | ... Q12: =Model!Q19/Model!Q7 -> 0.11382302
B14: Dupont / Earning Power
B15: Asset Turnover | D15: =Model!D7/AVERAGE(Model!C57:D57) -> 0.72185681 | E15: =Model!E7/AVERAGE(Model!D57:E57) -> 0.7379002 | F15: =Model!F7/AVERAGE(Model!E57:F57) -> 0.64780727 | G15: =Model!G7/AVERAGE(Model!F57:G57) -> 0.64354892 | H15: =Model!H7/AVERAGE(Model!G57:H57) -> 0.6683317 | I15: =Model!I7/AVERAGE(Model!H57:I57) -> 0.71774338 | J15: =Model!J7/AVERAGE(Model!I57:J57) -> 0.76224345 | K15: =Model!K7/AVERAGE(Model!J57:K57) -> 0.79840016 | ... Q15: =Model!Q7/AVERAGE(Model!P57:Q57) -> 0.85355885
B16: Pretax ROA | D16: =Model!D17/AVERAGE(Model!C57:D57) -> 0.084653261 | E16: =Model!E17/AVERAGE(Model!D57:E57) -> 0.098051621 | F16: =Model!F17/AVERAGE(Model!E57:F57) -> 0.06420603 | G16: =Model!G17/AVERAGE(Model!F57:G57) -> 0.079449325 | H16: =Model!H17/AVERAGE(Model!G57:H57) -> 0.083856325 | I16: =Model!I17/AVERAGE(Model!H57:I57) -> 0.093437416 | J16: =Model!J17/AVERAGE(Model!I57:J57) -> 0.10240735 | K16: =Model!K17/AVERAGE(Model!J57:K57) -> 0.11100916 | ... Q16: =Model!Q17/AVERAGE(Model!P57:Q57) -> 0.12965094
B17: Pretax ROE | D17: =Model!D17/AVERAGE(Model!C72:D72) -> 0.14158579 | E17: =Model!E17/AVERAGE(Model!D72:E72) -> 0.16450554 | F17: =Model!F17/AVERAGE(Model!E72:F72) -> 0.1149915 | G17: =Model!G17/AVERAGE(Model!F72:G72) -> 0.1483365 | H17: =Model!H17/AVERAGE(Model!G72:H72) -> 0.15219422 | I17: =Model!I17/AVERAGE(Model!H72:I72) -> 0.16391647 | J17: =Model!J17/AVERAGE(Model!I72:J72) -> 0.17260362 | K17: =Model!K17/AVERAGE(Model!J72:K72) -> 0.17912301 | ... Q17: =Model!Q17/AVERAGE(Model!P72:Q72) -> 0.17156846
B18: Tax Complement | C18: =Model!C19/Model!C17 -> 0.85772321 | D18: =Model!D19/Model!D17 -> 0.68409236 | E18: =Model!E19/Model!E17 -> 0.74334499 | F18: =Model!F19/Model!F17 -> 0.80227626 | G18: =Model!G19/Model!G17 -> 0.74935551 | H18: =Model!H19/Model!H17 -> 0.74935551 | I18: =Model!I19/Model!I17 -> 0.74935551 | J18: =Model!J19/Model!J17 -> 0.74935551 | ... Q18: =Model!Q19/Model!Q17 -> 0.74935551
B19: ROE | D19: =Model!D19/AVERAGE(Model!C72:D72) -> 0.096857755 | E19: =Model!E19/AVERAGE(Model!D72:E72) -> 0.12228437 | F19: =Model!F19/AVERAGE(Model!E72:F72) -> 0.092254949 | G19: =Model!G19/AVERAGE(Model!F72:G72) -> 0.11115678 | H19: =Model!H19/AVERAGE(Model!G72:H72) -> 0.11404758 | I19: =Model!I19/AVERAGE(Model!H72:I72) -> 0.12283171 | J19: =Model!J19/AVERAGE(Model!I72:J72) -> 0.12934147 | K19: =Model!K19/AVERAGE(Model!J72:K72) -> 0.13422681 | ... Q19: =Model!Q19/AVERAGE(Model!P72:Q72) -> 0.12856577
B20: Reinvestment Rate | D20: =(Model!D118+Model!D120-Model!D114)/(Model!D14*(1-Model!D34)) -> 0.68989575 | E20: =(Model!E118+Model!E120-Model!E114)/(Model!E14*(1-Model!E34)) -> 0.86843033 | F20: =(Model!F118+Model!F120-Model!F114)/(Model!F14*(1-Model!F34)) -> 0.8441667 | G20: =(Model!G118+Model!G120-Model!G114)/(Model!G14*(1-Model!G34)) -> 0.56788488 | H20: =(Model!H118+Model!H120-Model!H114)/(Model!H14*(1-Model!H34)) -> 0.58169048 | I20: =(Model!I118+Model!I120-Model!I114)/(Model!I14*(1-Model!I34)) -> 0.50918063 | J20: =(Model!J118+Model!J120-Model!J114)/(Model!J14*(1-Model!J34)) -> 0.31707397 | K20: =(Model!K118+Model!K120-Model!K114)/(Model!K14*(1-Model!K34)) -> 0.29718228 | ... Q20: =(Model!Q118+Model!Q120-Model!Q114)/(Model!Q14*(1-Model!Q34)) -> 0.18502736
B22: Liquidity Ratio
B23: Current Ratio | C23: =SUM(Model!C45:C49)/SUM(Model!C60:C61) -> 0.70273405 | D23: =SUM(Model!D45:D49)/SUM(Model!D60:D61) -> 0.71749859 | E23: =SUM(Model!E45:E49)/SUM(Model!E60:E61) -> 0.70516299 | F23: =SUM(Model!F45:F49)/SUM(Model!F60:F61) -> 0.77769504 | G23: =SUM(Model!G45:G49)/SUM(Model!G60:G61) -> 0.76420186 | H23: =SUM(Model!H45:H49)/SUM(Model!H60:H61) -> 0.83210488 | I23: =SUM(Model!I45:I49)/SUM(Model!I60:I61) -> 0.89596522 | J23: =SUM(Model!J45:J49)/SUM(Model!J60:J61) -> 1.0066226 | ... Q23: =SUM(Model!Q45:Q49)/SUM(Model!Q60:Q61) -> 2.4877101
B24: Quick Ratio | C24: =SUM(Model!C45:C47)/SUM(Model!C60:C61) -> 0.22664044 | D24: =SUM(Model!D45:D47)/SUM(Model!D60:D61) -> 0.26767945 | E24: =SUM(Model!E45:E47)/SUM(Model!E60:E61) -> 0.23267564 | F24: =SUM(Model!F45:F47)/SUM(Model!F60:F61) -> 0.30361432 | G24: =SUM(Model!G45:G47)/SUM(Model!G60:G61) -> 0.28680532 | H24: =SUM(Model!H45:H47)/SUM(Model!H60:H61) -> 0.32261904 | I24: =SUM(Model!I45:I47)/SUM(Model!I60:I61) -> 0.36609469 | J24: =SUM(Model!J45:J47)/SUM(Model!J60:J61) -> 0.45190579 | ... Q24: =SUM(Model!Q45:Q47)/SUM(Model!Q60:Q61) -> 1.8220253
B25: Cash Ratio | C25: =SUM(Model!C45:C46)/SUM(Model!C60:C61) -> 0.023727687 | D25: =SUM(Model!D45:D46)/SUM(Model!D60:D61) -> 0.06134055 | E25: =SUM(Model!E45:E46)/SUM(Model!E60:E61) -> 0.036004855 | F25: =SUM(Model!F45:F46)/SUM(Model!F60:F61) -> 0.067169856 | G25: =SUM(Model!G45:G46)/SUM(Model!G60:G61) -> 0.053559096 | H25: =SUM(Model!H45:H46)/SUM(Model!H60:H61) -> 0.077531169 | I25: =SUM(Model!I45:I46)/SUM(Model!I60:I61) -> 0.1015516 | J25: =SUM(Model!J45:J46)/SUM(Model!J60:J61) -> 0.1716932 | ... Q25: =SUM(Model!Q45:Q46)/SUM(Model!Q60:Q61) -> 1.4600006
B26: Cash Conversion Cycle | D26: =Model!D36+Model!D37-Model!D38 -> 14.428822 | E26: =Model!E36+Model!E37-Model!E38 -> 16.453147 | F26: =Model!F36+Model!F37-Model!F38 -> 24.925751 | G26: =Model!G36+Model!G37-Model!G38 -> 23.052789 | H26: =Model!H36+Model!H37-Model!H38 -> 23.98927 | I26: =Model!I36+Model!I37-Model!I38 -> 23.521029 | J26: =Model!J36+Model!J37-Model!J38 -> 23.755149 | K26: =Model!K36+Model!K37-Model!K38 -> 23.638089 | ... Q26: =Model!Q36+Model!Q37-Model!Q38 -> 23.6765
B28: Solvency Ratios
B29: Asset / Equity | C29: =Model!C57/Model!C72 -> 1.6620867 | D29: =Model!D57/Model!D72 -> 1.6822408 | E29: =Model!E57/Model!E72 -> 1.6736883 | F29: =Model!F57/Model!F72 -> 1.8908827 | G29: =Model!G57/Model!G72 -> 1.8450733 | H29: =Model!H57/Model!H72 -> 1.7871828 | I29: =Model!I57/Model!I72 -> 1.7241844 | J29: =Model!J57/Model!J72 -> 1.6501819 | ... Q29: =Model!Q57/Model!Q72 -> 1.3090799
B30: Debt / Equity | C30: =Model!C64/Model!C72 -> 0.22402577 | D30: =Model!D64/Model!D72 -> 0.20354963 | E30: =Model!E64/Model!E72 -> 0.18933138 | F30: =Model!F64/Model!F72 -> 0.34087784 | G30: =Model!G64/Model!G72 -> 0.31002339 | H30: =Model!H64/Model!H72 -> 0.28558331 | I30: =Model!I64/Model!I72 -> 0.25040494 | J30: =Model!J64/Model!J72 -> 0.20307109 | ... Q30: =Model!Q64/Model!Q72 -> 0.029273137
B31: Debt / Total Capital | C31: =Model!C64/SUM(Model!C64,Model!C72) -> 0.18302373 | D31: =Model!D64/SUM(Model!D64,Model!D72) -> 0.16912442 | E31: =Model!E64/SUM(Model!E64,Model!E72) -> 0.15919144 | F31: =Model!F64/SUM(Model!F64,Model!F72) -> 0.25421991 | G31: =Model!G64/SUM(Model!G64,Model!G72) -> 0.23665485 | H31: =Model!H64/SUM(Model!H64,Model!H72) -> 0.22214298 | I31: =Model!I64/SUM(Model!I64,Model!I72) -> 0.20025908 | J31: =Model!J64/SUM(Model!J64,Model!J72) -> 0.16879393 | ... Q31: =Model!Q64/SUM(Model!Q64,Model!Q72) -> 0.028440591
B32: Net Debt / EBITDA | C32: =Model!C140/Model!C12 -> 0.51902886 | D32: =Model!D140/Model!D12 -> 0.38339054 | E32: =Model!E140/Model!E12 -> 0.39595298 | F32: =Model!F140/Model!F12 -> 1.5584207 | G32: =Model!G140/Model!G12 -> 1.0948806 | H32: =Model!H140/Model!H12 -> 0.96832921 | I32: =Model!I140/Model!I12 -> 0.77585088 | J32: =Model!J140/Model!J12 -> 0.49470945 | ... Q32: =Model!Q140/Model!Q12 -> -1.4342304
B33: Interest Coverage | C33: =Model!C14/-Model!C127 -> 9.3146045 | D33: =Model!D14/-Model!D127 -> 9.397924 | E33: =Model!E14/-Model!E127 -> 10.147996 | F33: =Model!F14/-Model!F127 -> 5.1755789 | G33: =Model!G14/-Model!G127 -> 6.6120125 | H33: =Model!H14/-Model!H127 -> 7.2952002 | I33: =Model!I14/-Model!I127 -> 8.3952243 | J33: =Model!J14/-Model!J127 -> 9.9134828 | ... Q33: =Model!Q14/-Model!Q127 -> 56.021222
B35: Activity Ratios (Efficiency)
B36: Debtor Turnover Ratio | D36: =Model!D7/AVERAGE(Model!C47:D47) -> 18.228376 | E36: =Model!E7/AVERAGE(Model!D47:E47) -> 17.411068 | F36: =Model!F7/AVERAGE(Model!E47:F47) -> 14.939431 | G36: =Model!G7/AVERAGE(Model!F47:G47) -> 14.852174 | H36: =Model!H7/AVERAGE(Model!G47:H47) -> 15.463485 | I36: =Model!I7/AVERAGE(Model!H47:I47) -> 15.796513 | J36: =Model!J7/AVERAGE(Model!I47:J47) -> 15.704815 | K36: =Model!K7/AVERAGE(Model!J47:K47) -> 15.608699 | ... Q36: =Model!Q7/AVERAGE(Model!P47:Q47) -> 15.351946
B37: DSO | D37: =365/D36 -> 20.023725 | E37: =365/E36 -> 20.963677 | F37: =365/F36 -> 24.431988 | G37: =365/G36 -> 24.575527 | H37: =365/H36 -> 23.603993 | I37: =365/I36 -> 23.106366 | J37: =365/J36 -> 23.24128 | K37: =365/K36 -> 23.384396 | ... Q37: =365/Q36 -> 23.775488
B38: Inventory Turnover Ratio | D38: =-Model!D8/AVERAGE(Model!C48:D48) -> 4.6211735 | E38: =-Model!E8/AVERAGE(Model!D48:E48) -> 4.0405714 | F38: =-Model!F8/AVERAGE(Model!E48:F48) -> 3.5906089 | G38: =-Model!G8/AVERAGE(Model!F48:G48) -> 3.8204314 | H38: =-Model!H8/AVERAGE(Model!G48:H48) -> 3.9154331 | I38: =-Model!I8/AVERAGE(Model!H48:I48) -> 3.9614837 | J38: =-Model!J8/AVERAGE(Model!I48:J48) -> 3.952369 | K38: =-Model!K8/AVERAGE(Model!J48:K48) -> 3.9211169 | ... Q38: =-Model!Q8/AVERAGE(Model!P48:Q48) -> 3.8589276
B39: DSI | D39: =365/D38 -> 78.984266 | E39: =365/E38 -> 90.333759 | F39: =365/F38 -> 101.65407 | G39: =365/G38 -> 95.53895 | H39: =365/H38 -> 93.22085 | I39: =365/I38 -> 92.137196 | J39: =365/J38 -> 92.349677 | K39: =365/K38 -> 93.085722 | ... Q39: =365/Q38 -> 94.585864
B40: Payable Turnover Ratio | D40: =-Model!D8/AVERAGE(Model!C60:D60) -> 4.3154834 | E40: =-Model!E8/AVERAGE(Model!D60:E60) -> 3.848413 | F40: =-Model!F8/AVERAGE(Model!E60:F60) -> 3.6081346 | G40: =-Model!G8/AVERAGE(Model!F60:G60) -> 3.7604951 | H40: =-Model!H8/AVERAGE(Model!G60:H60) -> 3.8046308 | I40: =-Model!I8/AVERAGE(Model!H60:I60) -> 3.9300545 | J40: =-Model!J8/AVERAGE(Model!I60:J60) -> 3.9167823 | K40: =-Model!K8/AVERAGE(Model!J60:K60) -> 3.8879588 | ... Q40: =-Model!Q8/AVERAGE(Model!P60:Q60) -> 3.8255923
B41: DPO | D41: =365/D40 -> 84.579169 | E41: =365/E40 -> 94.844289 | F41: =365/F40 -> 101.1603 | G41: =365/G40 -> 97.061688 | H41: =365/H40 -> 95.935722 | I41: =365/I40 -> 92.874029 | J41: =365/J40 -> 93.188738 | K41: =365/K40 -> 93.879596 | ... Q41: =365/Q40 -> 95.410064
B42: Fixed Asset Turnover | D42: =Model!D7/AVERAGE(Model!C52:D52) -> 1.2616003 | E42: =Model!E7/AVERAGE(Model!D52:E52) -> 1.2947631 | F42: =Model!F7/AVERAGE(Model!E52:F52) -> 1.0784155 | G42: =Model!G7/AVERAGE(Model!F52:G52) -> 1.0273356 | H42: =Model!H7/AVERAGE(Model!G52:H52) -> 1.0563923 | I42: =Model!I7/AVERAGE(Model!H52:I52) -> 1.132012 | J42: =Model!J7/AVERAGE(Model!I52:J52) -> 1.2118882 | K42: =Model!K7/AVERAGE(Model!J52:K52) -> 1.2923016 | ... Q42: =Model!Q7/AVERAGE(Model!P52:Q52) -> 1.6948132

Sheet Market Return
B2: =Model!B2 -> UltraTech Cement Ltd
B3: Equity Market Return
C5: Index
B6: Date | C6: Close Price
E7: Index | F7: Nifty 50 TRI
B8: 46303 | C8: 33781.1 | E8: No. of Years | F8: =YEARFRAC(B8,B2480) -> 9.9944444
B9: 46302 | C9: 34345.16 | E9: CAGR | F9: =(C8/C2480)^(1/F8)-1 -> 0.11163968
B10: 46301 | C10: 34608.14
B11: 46300 | C11: 34273.35
B12: 46296 | C12: 34070.01
B13: 46295 | C13: 34371.66
B14: 46294 | C14: 34517.11
B15: 46293 | C15: 34614.46
B16: 46290 | C16: 35161.85
B17: 46289 | C17: 35044.24
B18: 46288 | C18: 35627.25
B19: 46287 | C19: 35448.24
B20: 46286 | C20: 35577.9
B21: 46283 | C21: 35474.68
... B2480: 42653 | C2480: 11729.75

Sheet Beta & WACC
B2: ='Market Return'!B2 -> UltraTech Cement Ltd
B3: Weighted Average Cost of Capital (WACC)
B5: Comparable Companies Beta
C7: Equity | D7: Total | E7: Debt/ | F7: Debt/ | G7: Tax | H7: Levered | I7: Unlevered
B8: Company Name | C8: Value | D8: Debt | E8: Equity | F8: Capital | G8: Rate % | H8: Beta | I8: Beta
B10: =Model!B185 -> Ambuja Cements | C10: =Model!E185 -> 86968 | D10: =Model!F185 -> 865.93 | E10: =D10/C10 -> 0.0099568807 | F10: =D10/SUM(C10:D10) -> 0.0098587186 | G10: ='Comps Data'!K4 -> 0.2705 | H10: 0.2 | I10: =H10/(1+E10*(1-G10)) -> 0.19855777
B11: =Model!B186 -> Shree Cement | C11: =Model!E186 -> 79943.45 | D11: =Model!F186 -> 1868.14 | E11: =D11/C11 -> 0.023368268 | F11: =D11/SUM(C11:D11) -> 0.022834662 | G11: ='Comps Data'!K5 -> 0.2592 | H11: 0.3 | I11: =H11/(1+E11*(1-G11)) -> 0.29489501
B12: =Model!B187 -> J K Cements | C12: =Model!E187 -> 37498.23 | D12: =Model!F187 -> 6182.99 | E12: =D12/C12 -> 0.16488752 | F12: =D12/SUM(C12:D12) -> 0.14154802 | G12: ='Comps Data'!K6 -> 0.3374 | H12: 0.39 | I12: =H12/(1+E12*(1-G12)) -> 0.3515875
B13: =Model!B188 -> Dalmia Bharat Ltd | C13: =Model!E188 -> 29989.736 | D13: =Model!F188 -> 7406 | E13: =D13/C13 -> 0.24695116 | F13: =D13/SUM(C13:D13) -> 0.19804397 | G13: ='Comps Data'!K7 -> 0.2375 | H13: 0.19 | I13: =H13/(1+E13*(1-G13)) -> 0.15989225
B14: =Model!B189 -> ACC | C14: =Model!E189 -> 21334.08 | D14: =Model!F189 -> 428.61 | E14: =D14/C14 -> 0.020090391 | F14: =D14/SUM(C14:D14) -> 0.019694716 | G14: ='Comps Data'!K8 -> 0.2577 | H14: 0.34 | I14: =H14/(1+E14*(1-G14)) -> 0.33500405
B15: =Model!B190 -> The Ramco Cement | C15: =Model!E190 -> 19126.122 | D15: =Model!F190 -> 3871.1 | E15: =D15/C15 -> 0.20239858 | F15: =D15/SUM(C15:D15) -> 0.16832903 | G15: ='Comps Data'!K9 -> 0.2508 | H15: 0.1 | I15: =H15/(1+E15*(1-G15)) -> 0.086832916
B17: Average | E17: =AVERAGE(E10:E15) -> 0.11127547 | F17: =AVERAGE(F10:F15) -> 0.093384851 | G17: =AVERAGE(G10:G15) -> 0.26885 | H17: =AVERAGE(H10:H15) -> 0.25333333 | I17: =AVERAGE(I10:I15) -> 0.23779491
B18: Median | E18: =MEDIAN(E10:E15) -> 0.094127892 | F18: =MEDIAN(F10:F15) -> 0.082191339 | G18: =MEDIAN(G10:G15) -> 0.25845 | H18: =MEDIAN(H10:H15) -> 0.25 | I18: =MEDIAN(I10:I15) -> 0.24672639
B20: =Model!B195 -> UltraTech Cem. | C20: =Model!E195 -> 314592.25 | D20: =Model!F195 -> 23755.09 | E20: =D20/C20 -> 0.075510729 | F20: =D20/SUM(C20:D20) -> 0.070209182 | G20: ='Comps Data'!K3 -> 0.2464 | H20: 0.49 | I20: =H20/(1+E20*(1-G20)) -> 0.46361788
A22: # | B22: WACC Calculation
B24: Target Capital Structure
B25: Proportion of Debt | D25: =F17 -> 0.093384851
B26: Proportion of Equity | D26: =1-D25 -> 0.90661515
B28: Current Capital Structure
B29: Market Cap. | D29: =C20 -> 314592.25
B30: Total Debt | D30: =D20 -> 23755.09
B31: Debt / Equity | D31: =D30/D29 -> 0.075510729
B33: Cost of Debt
B34: Pre Tax Cost of Debt | D34: =Model!H32 -> 0.078220509
B35: Tax Rate | D35: =G20 -> 0.2464
B36: After Tax Cost of Debt | D36: =D34*(1-D35) -> 0.058946975
B38: Beta
B39: Levered Beta from regression | D39: ='Beta from Regression'!I5 -> 1.2315352
B40: Unlevered Beta | D40: =D39/(1+E20*(1-G20)) -> 1.165228
B42: Relevered Beta | D42: =D40*(1+(D25/D26)*(1-G20)) -> 1.2556773
B44: Cost of Equity
B45: Risk Free Rate | D45: 0.07302
B46: Equity Market Return | D46: ='Market Return'!F9 -> 0.11163968
B47: Equity Risk Premium | D47: =D46-D45 -> 0.038619675
B48: Levered Equity Beta | D48: =D42 -> 1.2556773
B49: Cost of Equity | D49: =D45+D47*D48 -> 0.12151385
B51: WACC | D51: =D25*D36+D26*D49 -> 0.11567105

Sheet Beta from Regression
B2: ='Beta & WACC'!B2 -> UltraTech Cement Ltd
B3: Company Beta
C5: Index | D5: % Change | E5: Stock | F5: % Change | H5: Beta | I5: =SLOPE(F8:F67,D8:D67) -> 1.2315352
B6: Date | C6: Close Price | D6: Monthly | E6: Close Price | F6: Monthly
B7: 44470 | C7: 59306.93 | D7: NA | E7: 7632.75 | F7: NA
B8: 44501 | C8: 57064.87 | D8: =C8/C7-1 -> -0.037804351 | E8: 7434.4 | F8: =E8/E7-1 -> -0.025986702 | H8: SUMMARY OUTPUT
B9: 44531 | C9: 58253.82 | D9: =C9/C8-1 -> 0.02083506 | E9: 7591.95 | F9: =E9/E8-1 -> 0.021192026
B10: 44562 | C10: 58014.17 | D10: =C10/C9-1 -> -0.0041138933 | E10: 7214.45 | F10: =E10/E9-1 -> -0.049723721 | H10: Regression Statistics
B11: 44593 | C11: 56247.28 | D11: =C11/C10-1 -> -0.03045618 | E11: 6569.75 | F11: =E11/E10-1 -> -0.089362321 | H11: Multiple R | I11: 0.74275658
B12: 44621 | C12: 58568.51 | D12: =C12/C11-1 -> 0.041268307 | E12: 6602.15 | F12: =E12/E11-1 -> 0.0049316945 | H12: R Square | I12: 0.55168734
B13: 44652 | C13: 57060.87 | D13: =C13/C12-1 -> -0.025741478 | E13: 6629 | F13: =E13/E12-1 -> 0.004066857 | H13: Adjusted R Square | I13: 0.54395781
B14: 44682 | C14: 55566.41 | D14: =C14/C13-1 -> -0.026190628 | E14: 6083.1 | F14: =E14/E13-1 -> -0.082350279 | H14: Standard Error | I14: 0.042636761
B15: 44713 | C15: 53018.94 | D15: =C15/C14-1 -> -0.045845503 | E15: 5599.95 | F15: =E15/E14-1 -> -0.079424964 | H15: Observations | I15: 60
B16: 44743 | C16: 57570.25 | D16: =C16/C15-1 -> 0.085843097 | E16: 6545.9 | F16: =E16/E15-1 -> 0.16892115
B17: 44774 | C17: 59537.07 | D17: =C17/C16-1 -> 0.034163826 | E17: 6672.5 | F17: =E17/E16-1 -> 0.01934035 | H17: ANOVA
B18: 44805 | C18: 57426.92 | D18: =C18/C17-1 -> -0.035442624 | E18: 6249.85 | F18: =E18/E17-1 -> -0.063342076 | I18: df | J18: SS | K18: MS | L18: F | M18: Significance F
B19: 44835 | C19: 60746.59 | D19: =C19/C18-1 -> 0.057806861 | E19: 6713.35 | F19: =E19/E18-1 -> 0.07416178 | H19: Regression | I19: 1 | J19: 0.12975031 | K19: 0.12975031 | L19: 71.373994 | M19: 1.0905747e-11
B20: 44866 | C20: 63099.65 | D20: =C20/C19-1 -> 0.038735672 | E20: 7076.75 | F20: =E20/E19-1 -> 0.054130948 | H20: Residual | I20: 58 | J20: 0.10543782 | K20: 0.0018178934
B21: 44896 | C21: 60840.74 | D21: =C21/C20-1 -> -0.035799089 | E21: 6959.05 | F21: =E21/E20-1 -> -0.016631928 | H21: Total | I21: 59 | J21: 0.23518813
B22: 44927 | C22: 59549.9 | D22: =C22/C21-1 -> -0.021216704 | E22: 7089.1 | F22: =E22/E21-1 -> 0.018687896
B23: 44958 | C23: 58962.12 | D23: =C23/C22-1 -> -0.0098703776 | E23: 7263.05 | F23: =E23/E22-1 -> 0.024537671 | I23: Coefficients | J23: Standard Error | K23: t Stat | L23: P-value | M23: Lower 95% | N23: Upper 95% | O23: Lower 95.0% | P23: Upper 95.0%
B24: 44986 | C24: 58991.52 | D24: =C24/C23-1 -> 0.00049862522 | E24: 7620 | F24: =E24/E23-1 -> 0.04914602 | H24: Intercept | I24: 0.0025302198 | J24: 0.0055361498 | K24: 0.45703601 | L24: 0.6493524 | M24: -0.0085515881 | N24: 0.013612028 | O24: -0.0085515881 | P24: 0.013612028
B25: 45017 | C25: 61112.44 | D25: =C25/C24-1 -> 0.035952964 | E25: 7554.6 | F25: =E25/E24-1 -> -0.0085826772 | H25: X Variable 1 | I25: 1.2315352 | J25: 0.14577291 | K25: 8.4483131 | L25: 1.0905747e-11 | M25: 0.939739 | N25: 1.5233314 | O25: 0.939739 | P25: 1.5233314
B26: 45047 | C26: 62622.24 | D26: =C26/C25-1 -> 0.024705281 | E26: 7873.65 | F26: =E26/E25-1 -> 0.042232547
B27: 45078 | C27: 64718.56 | D27: =C27/C26-1 -> 0.033475647 | E27: 8292.85 | F27: =E27/E26-1 -> 0.053240873
B28: 45108 | C28: 66527.67 | D28: =C28/C27-1 -> 0.027953496 | E28: 8314.95 | F28: =E28/E27-1 -> 0.0026649463
B29: 45139 | C29: 64831.41 | D29: =C29/C28-1 -> -0.02549706 | E29: 8315.1 | F29: =E29/E28-1 -> 1.8039796e-05
B30: 45170 | C30: 65828.41 | D30: =C30/C29-1 -> 0.015378348 | E30: 8257.5 | F30: =E30/E29-1 -> -0.0069271566
B31: 45200 | C31: 63874.93 | D31: =C31/C30-1 -> -0.029675333 | E31: 8429.1 | F31: =E31/E30-1 -> 0.020781108
B32: 45231 | C32: 66988.44 | D32: =C32/C31-1 -> 0.04874385 | E32: 9000.65 | F32: =E32/E31-1 -> 0.067806765
B33: 45261 | C33: 72240.26 | D33: =C33/C32-1 -> 0.0783989 | E33: 10503.15 | F33: =E33/E32-1 -> 0.16693239
B34: 45292 | C34: 71752.11 | D34: =C34/C33-1 -> -0.0067573123 | E34: 10167.95 | F34: =E34/E33-1 -> -0.031914235
B35: 45323 | C35: 72500.3 | D35: =C35/C34-1 -> 0.010427429 | E35: 9901.9 | F35: =E35/E34-1 -> -0.02616555
B36: 45352 | C36: 73651.35 | D36: =C36/C35-1 -> 0.015876486 | E36: 9745.05 | F36: =E36/E35-1 -> -0.015840394
B37: 45383 | C37: 74482.78 | D37: =C37/C36-1 -> 0.011288727 | E37: 9966.75 | F37: =E37/E36-1 -> 0.022750012
... B67: 46296 | C67: 72472.33 | D67: =C67/C66-1 -> -0.00010982296 | E67: 10680 | F67: =E67/E66-1 -> -0.026879271
